Workbook
Name AcceptedCmp1: 'Data Cleaning'!$AE$2:$AE$2237
Name AcceptedCmp2: 'Data Cleaning'!$AF$2:$AF$2237
Name AcceptedCmp3: 'Data Cleaning'!$AB$2:$AB$2237
Name AcceptedCmp4: 'Data Cleaning'!$AC$2:$AC$2237
Name AcceptedCmp5: 'Data Cleaning'!$AD$2:$AD$2237
Name Age: 'Data Cleaning'!$C$2:$C$2237
Name Age_Group: 'Data Cleaning'!$D$2:$D$2237
Name Complain: 'Data Cleaning'!$AH$2:$AH$2237
Name Dt_Customer: 'Data Cleaning'!$N$2:$N$2237
Name Education: 'Data Cleaning'!$E$2:$E$2237
Name HasChildren: 'Data Cleaning'!$M$2:$M$2237
Name ID: 'Data Cleaning'!$A$2:$A$2237
Name Income: 'Data Cleaning'!$G$2:$G$2237
Name Income_Clean: 'Data Cleaning'!$H$2:$H$2237
Name Income_Segment: 'Data Cleaning'!$I$2:$I$2237
Name Kidhome: 'Data Cleaning'!$K$2:$K$2237
Name Marital_Status: 'Data Cleaning'!$F$2:$F$2237
Name MntFishProducts: 'Data Cleaning'!$S$2:$S$2237
Name MntFruits: 'Data Cleaning'!$Q$2:$Q$2237
Name MntGoldProds: 'Data Cleaning'!$U$2:$U$2237
Name MntMeatProducts: 'Data Cleaning'!$R$2:$R$2237
Name MntSweetProducts: 'Data Cleaning'!$T$2:$T$2237
Name MntWines: 'Data Cleaning'!$P$2:$P$2237
Name NumCatalogPurchases: 'Data Cleaning'!$Y$2:$Y$2237
Name NumDealsPurchases: 'Data Cleaning'!$W$2:$W$2237
Name NumStorePurchases: 'Data Cleaning'!$Z$2:$Z$2237
Name NumWebPurchases: 'Data Cleaning'!$X$2:$X$2237
Name NumWebVisitsMonth: 'Data Cleaning'!$AA$2:$AA$2237
Name Recency: 'Data Cleaning'!$O$2:$O$2237
Name Response: 'Data Cleaning'!$AI$2:$AI$2237
Name Slicer_Age_Group: #N/A
Name Slicer_Income_Segment: #N/A
Name Teenhome: 'Data Cleaning'!$L$2:$L$2237
Name TotalCampaigns: 'Data Cleaning'!$AG$2:$AG$2237
Name TotalSpend: 'Data Cleaning'!$V$2:$V$2237
Name Year_Birth: 'Data Cleaning'!$B$2:$B$2237

Sheet Raw Data
A1: ID | B1: Year_Birth | C1: Education | D1: Marital_Status | E1: Income | F1: Kidhome | G1: Teenhome | H1: Dt_Customer | I1: Recency | J1: MntWines | K1: MntFruits | L1: MntMeatProducts | M1: MntFishProducts | N1: MntSweetProducts | O1: MntGoldProds | P1: NumDealsPurchases | Q1: NumWebPurchases | R1: NumCatalogPurchases | S1: NumStorePurchases | T1: NumWebVisitsMonth | U1: AcceptedCmp3 | V1: AcceptedCmp4 | W1: AcceptedCmp5 | X1: AcceptedCmp1 | Y1: AcceptedCmp2 | Z1: Complain | AA1: Z_CostContact | AB1: Z_Revenue | AC1: Response
A2: 5524 | B2: 1957 | C2: Graduation | D2: Single | E2: 58138 | F2: 0 | G2: 0 | H2: 2012-09-04 | I2: 58 | J2: 635 | K2: 88 | L2: 546 | M2: 172 | N2: 88 | O2: 88 | P2: 3 | Q2: 8 | R2: 10 | S2: 4 | T2: 7 | U2: 0 | V2: 0 | W2: 0 | X2: 0 | Y2: 0 | Z2: 0 | AA2: 3 | AB2: 11 | AC2: 1
A3: 2174 | B3: 1954 | C3: Graduation | D3: Single | E3: 46344 | F3: 1 | G3: 1 | H3: 2014-03-08 | I3: 38 | J3: 11 | K3: 1 | L3: 6 | M3: 2 | N3: 1 | O3: 6 | P3: 2 | Q3: 1 | R3: 1 | S3: 2 | T3: 5 | U3: 0 | V3: 0 | W3: 0 | X3: 0 | Y3: 0 | Z3: 0 | AA3: 3 | AB3: 11 | AC3: 0
A4: 4141 | B4: 1965 | C4: Graduation | D4: Together | E4: 71613 | F4: 0 | G4: 0 | H4: 2013-08-21 | I4: 26 | J4: 426 | K4: 49 | L4: 127 | M4: 111 | N4: 21 | O4: 42 | P4: 1 | Q4: 8 | R4: 2 | S4: 10 | T4: 4 | U4: 0 | V4: 0 | W4: 0 | X4: 0 | Y4: 0 | Z4: 0 | AA4: 3 | AB4: 11 | AC4: 0
A5: 6182 | B5: 1984 | C5: Graduation | D5: Together | E5: 26646 | F5: 1 | G5: 0 | H5: 2014-02-10 | I5: 26 | J5: 11 | K5: 4 | L5: 20 | M5: 10 | N5: 3 | O5: 5 | P5: 2 | Q5: 2 | R5: 0 | S5: 4 | T5: 6 | U5: 0 | V5: 0 | W5: 0 | X5: 0 | Y5: 0 | Z5: 0 | AA5: 3 | AB5: 11 | AC5: 0
A6: 5324 | B6: 1981 | C6: PhD | D6: Married | E6: 58293 | F6: 1 | G6: 0 | H6: 2014-01-19 | I6: 94 | J6: 173 | K6: 43 | L6: 118 | M6: 46 | N6: 27 | O6: 15 | P6: 5 | Q6: 5 | R6: 3 | S6: 6 | T6: 5 | U6: 0 | V6: 0 | W6: 0 | X6: 0 | Y6: 0 | Z6: 0 | AA6: 3 | AB6: 11 | AC6: 0
A7: 7446 | B7: 1967 | C7: Master | D7: Together | E7: 62513 | F7: 0 | G7: 1 | H7: 2013-09-09 | I7: 16 | J7: 520 | K7: 42 | L7: 98 | M7: 0 | N7: 42 | O7: 14 | P7: 2 | Q7: 6 | R7: 4 | S7: 10 | T7: 6 | U7: 0 | V7: 0 | W7: 0 | X7: 0 | Y7: 0 | Z7: 0 | AA7: 3 | AB7: 11 | AC7: 0
A8: 965 | B8: 1971 | C8: Graduation | D8: Divorced | E8: 55635 | F8: 0 | G8: 1 | H8: 2012-11-13 | I8: 34 | J8: 235 | K8: 65 | L8: 164 | M8: 50 | N8: 49 | O8: 27 | P8: 4 | Q8: 7 | R8: 3 | S8: 7 | T8: 6 | U8: 0 | V8: 0 | W8: 0 | X8: 0 | Y8: 0 | Z8: 0 | AA8: 3 | AB8: 11 | AC8: 0
A9: 6177 | B9: 1985 | C9: PhD | D9: Married | E9: 33454 | F9: 1 | G9: 0 | H9: 2013-05-08 | I9: 32 | J9: 76 | K9: 10 | L9: 56 | M9: 3 | N9: 1 | O9: 23 | P9: 2 | Q9: 4 | R9: 0 | S9: 4 | T9: 8 | U9: 0 | V9: 0 | W9: 0 | X9: 0 | Y9: 0 | Z9: 0 | AA9: 3 | AB9: 11 | AC9: 0
A10: 4855 | B10: 1974 | C10: PhD | D10: Together | E10: 30351 | F10: 1 | G10: 0 | H10: 2013-06-06 | I10: 19 | J10: 14 | K10: 0 | L10: 24 | M10: 3 | N10: 3 | O10: 2 | P10: 1 | Q10: 3 | R10: 0 | S10: 2 | T10: 9 | U10: 0 | V10: 0 | W10: 0 | X10: 0 | Y10: 0 | Z10: 0 | AA10: 3 | AB10: 11 | AC10: 1
A11: 5899 | B11: 1950 | C11: PhD | D11: Together | E11: 5648 | F11: 1 | G11: 1 | H11: 2014-03-13 | I11: 68 | J11: 28 | K11: 0 | L11: 6 | M11: 1 | N11: 1 | O11: 13 | P11: 1 | Q11: 1 | R11: 0 | S11: 0 | T11: 20 | U11: 1 | V11: 0 | W11: 0 | X11: 0 | Y11: 0 | Z11: 0 | AA11: 3 | AB11: 11 | AC11: 0
A12: 1994 | B12: 1983 | C12: Graduation | D12: Married | F12: 1 | G12: 0 | H12: 2013-11-15 | I12: 11 | J12: 5 | K12: 5 | L12: 6 | M12: 0 | N12: 2 | O12: 1 | P12: 1 | Q12: 1 | R12: 0 | S12: 2 | T12: 7 | U12: 0 | V12: 0 | W12: 0 | X12: 0 | Y12: 0 | Z12: 0 | AA12: 3 | AB12: 11 | AC12: 0
A13: 387 | B13: 1976 | C13: Basic | D13: Married | E13: 7500 | F13: 0 | G13: 0 | H13: 2012-11-13 | I13: 59 | J13: 6 | K13: 16 | L13: 11 | M13: 11 | N13: 1 | O13: 16 | P13: 1 | Q13: 2 | R13: 0 | S13: 3 | T13: 8 | U13: 0 | V13: 0 | W13: 0 | X13: 0 | Y13: 0 | Z13: 0 | AA13: 3 | AB13: 11 | AC13: 0
A14: 2125 | B14: 1959 | C14: Graduation | D14: Divorced | E14: 63033 | F14: 0 | G14: 0 | H14: 2013-11-15 | I14: 82 | J14: 194 | K14: 61 | L14: 480 | M14: 225 | N14: 112 | O14: 30 | P14: 1 | Q14: 3 | R14: 4 | S14: 8 | T14: 2 | U14: 0 | V14: 0 | W14: 0 | X14: 0 | Y14: 0 | Z14: 0 | AA14: 3 | AB14: 11 | AC14: 0
A15: 8180 | B15: 1952 | C15: Master | D15: Divorced | E15: 59354 | F15: 1 | G15: 1 | H15: 2013-11-15 | I15: 53 | J15: 233 | K15: 2 | L15: 53 | M15: 3 | N15: 5 | O15: 14 | P15: 3 | Q15: 6 | R15: 1 | S15: 5 | T15: 6 | U15: 0 | V15: 0 | W15: 0 | X15: 0 | Y15: 0 | Z15: 0 | AA15: 3 | AB15: 11 | AC15: 0
A16: 2569 | B16: 1987 | C16: Graduation | D16: Married | E16: 17323 | F16: 0 | G16: 0 | H16: 2012-10-10 | I16: 38 | J16: 3 | K16: 14 | L16: 17 | M16: 6 | N16: 1 | O16: 5 | P16: 1 | Q16: 1 | R16: 0 | S16: 3 | T16: 8 | U16: 0 | V16: 0 | W16: 0 | X16: 0 | Y16: 0 | Z16: 0 | AA16: 3 | AB16: 11 | AC16: 0
A17: 2114 | B17: 1946 | C17: PhD | D17: Single | E17: 82800 | F17: 0 | G17: 0 | H17: 2012-11-24 | I17: 23 | J17: 1006 | K17: 22 | L17: 115 | M17: 59 | N17: 68 | O17: 45 | P17: 1 | Q17: 7 | R17: 6 | S17: 12 | T17: 3 | U17: 0 | V17: 0 | W17: 1 | X17: 1 | Y17: 0 | Z17: 0 | AA17: 3 | AB17: 11 | AC17: 1
A18: 9736 | B18: 1980 | C18: Graduation | D18: Married | E18: 41850 | F18: 1 | G18: 1 | H18: 2012-12-24 | I18: 51 | J18: 53 | K18: 5 | L18: 19 | M18: 2 | N18: 13 | O18: 4 | P18: 3 | Q18: 3 | R18: 0 | S18: 3 | T18: 8 | U18: 0 | V18: 0 | W18: 0 | X18: 0 | Y18: 0 | Z18: 0 | AA18: 3 | AB18: 11 | AC18: 0
A19: 4939 | B19: 1946 | C19: Graduation | D19: Together | E19: 37760 | F19: 0 | G19: 0 | H19: 2012-08-31 | I19: 20 | J19: 84 | K19: 5 | L19: 38 | M19: 150 | N19: 12 | O19: 28 | P19: 2 | Q19: 4 | R19: 1 | S19: 6 | T19: 7 | U19: 0 | V19: 0 | W19: 0 | X19: 0 | Y19: 0 | Z19: 0 | AA19: 3 | AB19: 11 | AC19: 0
A20: 6565 | B20: 1949 | C20: Master | D20: Married | E20: 76995 | F20: 0 | G20: 1 | H20: 2013-03-28 | I20: 91 | J20: 1012 | K20: 80 | L20: 498 | M20: 0 | N20: 16 | O20: 176 | P20: 2 | Q20: 11 | R20: 4 | S20: 9 | T20: 5 | U20: 0 | V20: 0 | W20: 0 | X20: 1 | Y20: 0 | Z20: 0 | AA20: 3 | AB20: 11 | AC20: 0
A21: 2278 | B21: 1985 | C21: 2n Cycle | D21: Single | E21: 33812 | F21: 1 | G21: 0 | H21: 2012-11-03 | I21: 86 | J21: 4 | K21: 17 | L21: 19 | M21: 30 | N21: 24 | O21: 39 | P21: 2 | Q21: 2 | R21: 1 | S21: 3 | T21: 6 | U21: 0 | V21: 0 | W21: 0 | X21: 0 | Y21: 0 | Z21: 0 | AA21: 3 | AB21: 11 | AC21: 0
A22: 9360 | B22: 1982 | C22: Graduation | D22: Married | E22: 37040 | F22: 0 | G22: 0 | H22: 2012-08-08 | I22: 41 | J22: 86 | K22: 2 | L22: 73 | M22: 69 | N22: 38 | O22: 48 | P22: 1 | Q22: 4 | R22: 2 | S22: 5 | T22: 8 | U22: 0 | V22: 0 | W22: 0 | X22: 0 | Y22: 0 | Z22: 0 | AA22: 3 | AB22: 11 | AC22: 0
A23: 5376 | B23: 1979 | C23: Graduation | D23: Married | E23: 2447 | F23: 1 | G23: 0 | H23: 2013-01-06 | I23: 42 | J23: 1 | K23: 1 | L23: 1725 | M23: 1 | N23: 1 | O23: 1 | P23: 15 | Q23: 0 | R23: 28 | S23: 0 | T23: 1 | U23: 0 | V23: 0 | W23: 0 | X23: 0 | Y23: 0 | Z23: 0 | AA23: 3 | AB23: 11 | AC23: 0
A24: 1993 | B24: 1949 | C24: PhD | D24: Married | E24: 58607 | F24: 0 | G24: 1 | H24: 2012-12-23 | I24: 63 | J24: 867 | K24: 0 | L24: 86 | M24: 0 | N24: 0 | O24: 19 | P24: 3 | Q24: 2 | R24: 3 | S24: 9 | T24: 8 | U24: 0 | V24: 1 | W24: 0 | X24: 0 | Y24: 0 | Z24: 0 | AA24: 3 | AB24: 11 | AC24: 0
... A28: 2404 | B28: 1976 | C28: Graduation | D28: Married | E28: 53359 | F28: 1 | G28: 1 | H28: 2013-05-27 | I28: 4 | J28: 173 | K28: 4 | L28: 30 | M28: 3 | N28: 6 | O28: 41 | P28: 4 | Q28: 5 | R28: 1 | S28: 4 | T28: 7 | U28: 0 | V28: 0 | W28: 0 | X28: 0 | Y28: 0 | Z28: 0 | AA28: 3 | AB28: 11 | AC28: 0
A29: 5255 | B29: 1986 | C29: Graduation | D29: Single | F29: 1 | G29: 0 | H29: 2013-02-20 | I29: 19 | J29: 5 | K29: 1 | L29: 3 | M29: 3 | N29: 263 | O29: 362 | P29: 0 | Q29: 27 | R29: 0 | S29: 0 | T29: 1 | U29: 0 | V29: 0 | W29: 0 | X29: 0 | Y29: 0 | Z29: 0 | AA29: 3 | AB29: 11 | AC29: 0
A30: 9422 | B30: 1989 | C30: Graduation | D30: Married | E30: 38360 | F30: 1 | G30: 0 | H30: 2013-05-31 | I30: 26 | J30: 36 | K30: 2 | L30: 42 | M30: 20 | N30: 21 | O30: 10 | P30: 2 | Q30: 2 | R30: 1 | S30: 4 | T30: 3 | U30: 0 | V30: 0 | W30: 0 | X30: 0 | Y30: 0 | Z30: 0 | AA30: 3 | AB30: 11 | AC30: 0
A31: 1966 | B31: 1965 | C31: PhD | D31: Married | E31: 84618 | F31: 0 | G31: 0 | H31: 2013-11-22 | I31: 96 | J31: 684 | K31: 100 | L31: 801 | M31: 21 | N31: 66 | O31: 0 | P31: 1 | Q31: 6 | R31: 9 | S31: 10 | T31: 2 | U31: 0 | V31: 0 | W31: 1 | X31: 0 | Y31: 0 | Z31: 0 | AA31: 3 | AB31: 11 | AC31: 0
A32: 6864 | B32: 1989 | C32: Master | D32: Divorced | E32: 10979 | F32: 0 | G32: 0 | H32: 2014-05-22 | I32: 34 | J32: 8 | K32: 4 | L32: 10 | M32: 2 | N32: 2 | O32: 4 | P32: 2 | Q32: 3 | R32: 0 | S32: 3 | T32: 5 | U32: 0 | V32: 0 | W32: 0 | X32: 0 | Y32: 0 | Z32: 0 | AA32: 3 | AB32: 11 | AC32: 0
A33: 3033 | B33: 1963 | C33: Master | D33: Together | E33: 38620 | F33: 0 | G33: 0 | H33: 2013-05-11 | I33: 56 | J33: 112 | K33: 17 | L33: 44 | M33: 34 | N33: 22 | O33: 89 | P33: 1 | Q33: 2 | R33: 5 | S33: 3 | T33: 3 | U33: 0 | V33: 0 | W33: 0 | X33: 0 | Y33: 0 | Z33: 0 | AA33: 3 | AB33: 11 | AC33: 0
A34: 5710 | B34: 1970 | C34: Graduation | D34: Together | E34: 40548 | F34: 0 | G34: 1 | H34: 2012-10-10 | I34: 31 | J34: 110 | K34: 0 | L34: 5 | M34: 2 | N34: 0 | O34: 3 | P34: 2 | Q34: 2 | R34: 1 | S34: 4 | T34: 5 | U34: 0 | V34: 1 | W34: 0 | X34: 0 | Y34: 0 | Z34: 0 | AA34: 3 | AB34: 11 | AC34: 0
A35: 7373 | B35: 1952 | C35: PhD | D35: Divorced | E35: 46610 | F35: 0 | G35: 2 | H35: 2012-10-29 | I35: 8 | J35: 96 | K35: 12 | L35: 96 | M35: 33 | N35: 22 | O35: 43 | P35: 6 | Q35: 4 | R35: 1 | S35: 6 | T35: 6 | U35: 0 | V35: 0 | W35: 0 | X35: 0 | Y35: 0 | Z35: 0 | AA35: 3 | AB35: 11 | AC35: 1
A36: 8755 | B36: 1946 | C36: Master | D36: Married | E36: 68657 | F36: 0 | G36: 0 | H36: 2013-02-20 | I36: 4 | J36: 482 | K36: 34 | L36: 471 | M36: 119 | N36: 68 | O36: 22 | P36: 1 | Q36: 3 | R36: 5 | S36: 9 | T36: 7 | U36: 0 | V36: 0 | W36: 0 | X36: 0 | Y36: 0 | Z36: 0 | AA36: 3 | AB36: 11 | AC36: 0
A37: 10738 | B37: 1951 | C37: Master | D37: Single | E37: 49389 | F37: 1 | G37: 1 | H37: 2013-08-29 | I37: 55 | J37: 40 | K37: 0 | L37: 19 | M37: 2 | N37: 1 | O37: 3 | P37: 1 | Q37: 2 | R37: 0 | S37: 3 | T37: 7 | U37: 0 | V37: 0 | W37: 0 | X37: 0 | Y37: 0 | Z37: 0 | AA37: 3 | AB37: 11 | AC37: 0
A38: 4339 | B38: 1970 | C38: PhD | D38: Married | E38: 67353 | F38: 0 | G38: 1 | H38: 2013-12-31 | I38: 37 | J38: 702 | K38: 17 | L38: 151 | M38: 0 | N38: 8 | O38: 35 | P38: 5 | Q38: 5 | R38: 6 | S38: 12 | T38: 2 | U38: 0 | V38: 0 | W38: 0 | X38: 0 | Y38: 0 | Z38: 0 | AA38: 3 | AB38: 11 | AC38: 0
A39: 10755 | B39: 1976 | C39: 2n Cycle | D39: Married | E39: 23718 | F39: 1 | G39: 0 | H39: 2013-09-02 | I39: 76 | J39: 6 | K39: 3 | L39: 14 | M39: 15 | N39: 7 | O39: 36 | P39: 3 | Q39: 3 | R39: 1 | S39: 2 | T39: 7 | U39: 0 | V39: 0 | W39: 0 | X39: 0 | Y39: 0 | Z39: 0 | AA39: 3 | AB39: 11 | AC39: 0
A40: 8595 | B40: 1973 | C40: Graduation | D40: Widow | E40: 42429 | F40: 0 | G40: 1 | H40: 2014-02-11 | I40: 99 | J40: 55 | K40: 0 | L40: 6 | M40: 2 | N40: 0 | O40: 4 | P40: 2 | Q40: 1 | R40: 1 | S40: 3 | T40: 5 | U40: 0 | V40: 0 | W40: 0 | X40: 0 | Y40: 0 | Z40: 0 | AA40: 3 | AB40: 11 | AC40: 0
A41: 2968 | B41: 1943 | C41: PhD | D41: Divorced | E41: 48948 | F41: 0 | G41: 0 | H41: 2013-02-01 | I41: 53 | J41: 437 | K41: 8 | L41: 206 | M41: 160 | N41: 49 | O41: 42 | P41: 2 | Q41: 7 | R41: 10 | S41: 5 | T41: 6 | U41: 1 | V41: 0 | W41: 0 | X41: 0 | Y41: 0 | Z41: 0 | AA41: 3 | AB41: 11 | AC41: 1
... A44: 8430 | B44: 1957 | C44: Graduation | D44: Together | E44: 21994 | F44: 0 | G44: 1 | H44: 2012-12-24 | I44: 4 | J44: 9 | K44: 0 | L44: 6 | M44: 3 | N44: 1 | O44: 3 | P44: 1 | Q44: 0 | R44: 0 | S44: 3 | T44: 5 | U44: 0 | V44: 0 | W44: 0 | X44: 0 | Y44: 0 | Z44: 0 | AA44: 3 | AB44: 11 | AC44: 0
A45: 7281 | B45: 1959 | C45: PhD | D45: Single | F45: 0 | G45: 0 | H45: 2013-11-05 | I45: 80 | J45: 81 | K45: 11 | L45: 50 | M45: 3 | N45: 2 | O45: 39 | P45: 1 | Q45: 1 | R45: 3 | S45: 4 | T45: 2 | U45: 0 | V45: 0 | W45: 0 | X45: 0 | Y45: 0 | Z45: 0 | AA45: 3 | AB45: 11 | AC45: 0
A46: 2139 | B46: 1975 | C46: Master | D46: Married | E46: 7500 | F46: 1 | G46: 0 | H46: 2013-10-02 | I46: 19 | J46: 3 | K46: 1 | L46: 10 | M46: 3 | N46: 2 | O46: 12 | P46: 3 | Q46: 2 | R46: 0 | S46: 3 | T46: 5 | U46: 0 | V46: 0 | W46: 0 | X46: 0 | Y46: 0 | Z46: 0 | AA46: 3 | AB46: 11 | AC46: 0
A47: 1371 | B47: 1976 | C47: Graduation | D47: Single | E47: 79941 | F47: 0 | G47: 0 | H47: 2014-06-28 | I47: 72 | J47: 123 | K47: 164 | L47: 266 | M47: 227 | N47: 30 | O47: 174 | P47: 1 | Q47: 2 | R47: 4 | S47: 9 | T47: 1 | U47: 0 | V47: 0 | W47: 0 | X47: 0 | Y47: 0 | Z47: 0 | AA47: 3 | AB47: 11 | AC47: 0
A48: 9909 | B48: 1996 | C48: 2n Cycle | D48: Married | E48: 7500 | F48: 0 | G48: 0 | H48: 2012-11-09 | I48: 24 | J48: 3 | K48: 18 | L48: 14 | M48: 15 | N48: 22 | O48: 50 | P48: 3 | Q48: 3 | R48: 1 | S48: 3 | T48: 9 | U48: 0 | V48: 0 | W48: 0 | X48: 0 | Y48: 0 | Z48: 0 | AA48: 3 | AB48: 11 | AC48: 1
A49: 7286 | B49: 1968 | C49: Graduation | D49: Together | E49: 41728 | F49: 1 | G49: 0 | H49: 2013-05-24 | I49: 92 | J49: 13 | K49: 6 | L49: 15 | M49: 3 | N49: 5 | O49: 13 | P49: 1 | Q49: 2 | R49: 0 | S49: 2 | T49: 10 | U49: 0 | V49: 0 | W49: 0 | X49: 0 | Y49: 0 | Z49: 0 | AA49: 3 | AB49: 11 | AC49: 0
A50: 7244 | B50: 1951 | C50: Graduation | D50: Single | F50: 2 | G50: 1 | H50: 2014-01-01 | I50: 96 | J50: 48 | K50: 5 | L50: 48 | M50: 6 | N50: 10 | O50: 7 | P50: 3 | Q50: 2 | R50: 1 | S50: 4 | T50: 6 | U50: 0 | V50: 0 | W50: 0 | X50: 0 | Y50: 0 | Z50: 0 | AA50: 3 | AB50: 11 | AC50: 0
A51: 6566 | B51: 1954 | C51: PhD | D51: Married | E51: 72550 | F51: 1 | G51: 1 | H51: 2012-11-08 | I51: 39 | J51: 826 | K51: 50 | L51: 317 | M51: 50 | N51: 38 | O51: 38 | P51: 9 | Q51: 5 | R51: 2 | S51: 12 | T51: 8 | U51: 0 | V51: 0 | W51: 0 | X51: 0 | Y51: 0 | Z51: 0 | AA51: 3 | AB51: 11 | AC51: 0
A52: 8614 | B52: 1957 | C52: Graduation | D52: Widow | E52: 65486 | F52: 0 | G52: 1 | H52: 2014-05-12 | I52: 29 | J52: 245 | K52: 19 | L52: 125 | M52: 37 | N52: 67 | O52: 14 | P52: 1 | Q52: 4 | R52: 2 | S52: 10 | T52: 2 | U52: 0 | V52: 0 | W52: 0 | X52: 0 | Y52: 0 | Z52: 0 | AA52: 3 | AB52: 11 | AC52: 0
A53: 4114 | B53: 1964 | C53: Master | D53: Married | E53: 79143 | F53: 0 | G53: 0 | H53: 2012-08-11 | I53: 2 | J53: 650 | K53: 37 | L53: 780 | M53: 27 | N53: 167 | O53: 32 | P53: 1 | Q53: 6 | R53: 9 | S53: 13 | T53: 3 | U53: 0 | V53: 0 | W53: 0 | X53: 0 | Y53: 0 | Z53: 0 | AA53: 3 | AB53: 11 | AC53: 0
A54: 1331 | B54: 1977 | C54: Graduation | D54: Single | E54: 35790 | F54: 1 | G54: 0 | H54: 2013-01-02 | I54: 54 | J54: 12 | K54: 6 | L54: 20 | M54: 30 | N54: 1 | O54: 3 | P54: 2 | Q54: 2 | R54: 0 | S54: 3 | T54: 7 | U54: 0 | V54: 0 | W54: 0 | X54: 0 | Y54: 0 | Z54: 0 | AA54: 3 | AB54: 11 | AC54: 0
A55: 2225 | B55: 1977 | C55: Graduation | D55: Divorced | E55: 82582 | F55: 0 | G55: 0 | H55: 2014-06-07 | I55: 54 | J55: 510 | K55: 120 | L55: 550 | M55: 156 | N55: 40 | O55: 241 | P55: 1 | Q55: 4 | R55: 9 | S55: 7 | T55: 1 | U55: 1 | V55: 0 | W55: 0 | X55: 1 | Y55: 0 | Z55: 0 | AA55: 3 | AB55: 11 | AC55: 1
A56: 9381 | B56: 1978 | C56: Graduation | D56: Married | E56: 66373 | F56: 1 | G56: 1 | H56: 2013-06-12 | I56: 57 | J56: 328 | K56: 9 | L56: 124 | M56: 12 | N56: 24 | O56: 109 | P56: 7 | Q56: 4 | R56: 2 | S56: 10 | T56: 3 | U56: 0 | V56: 0 | W56: 0 | X56: 0 | Y56: 0 | Z56: 0 | AA56: 3 | AB56: 11 | AC56: 0
A57: 6260 | B57: 1955 | C57: Master | D57: Together | E57: 82384 | F57: 0 | G57: 0 | H57: 2012-11-19 | I57: 55 | J57: 984 | K57: 51 | L57: 432 | M57: 180 | N57: 120 | O57: 190 | P57: 1 | Q57: 3 | R57: 10 | S57: 13 | T57: 1 | U57: 0 | V57: 0 | W57: 1 | X57: 0 | Y57: 0 | Z57: 0 | AA57: 3 | AB57: 11 | AC57: 1
A58: 10383 | B58: 1966 | C58: Graduation | D58: Divorced | E58: 70287 | F58: 0 | G58: 0 | H58: 2013-04-02 | I58: 30 | J58: 295 | K58: 35 | L58: 482 | M58: 121 | N58: 120 | O58: 40 | P58: 1 | Q58: 5 | R58: 5 | S58: 10 | T58: 3 | U58: 0 | V58: 0 | W58: 0 | X58: 0 | Y58: 0 | Z58: 0 | AA58: 3 | AB58: 11 | AC58: 1
A59: 7437 | B59: 1988 | C59: Graduation | D59: Single | E59: 27938 | F59: 1 | G59: 0 | H59: 2014-04-28 | I59: 31 | J59: 13 | K59: 0 | L59: 8 | M59: 2 | N59: 1 | O59: 5 | P59: 1 | Q59: 1 | R59: 0 | S59: 4 | T59: 3 | U59: 0 | V59: 0 | W59: 0 | X59: 0 | Y59: 0 | Z59: 0 | AA59: 3 | AB59: 11 | AC59: 0
A60: 8557 | B60: 1982 | C60: Graduation | D60: Single | F60: 1 | G60: 0 | H60: 2013-06-17 | I60: 57 | J60: 11 | K60: 3 | L60: 22 | M60: 2 | N60: 2 | O60: 6 | P60: 2 | Q60: 2 | R60: 0 | S60: 3 | T60: 6 | U60: 0 | V60: 0 | W60: 0 | X60: 0 | Y60: 0 | Z60: 0 | AA60: 3 | AB60: 11 | AC60: 0
A61: 8375 | B61: 1968 | C61: PhD | D61: Married | E61: 55954 | F61: 0 | G61: 1 | H61: 2014-03-03 | I61: 63 | J61: 447 | K61: 0 | L61: 28 | M61: 0 | N61: 0 | O61: 43 | P61: 3 | Q61: 8 | R61: 2 | S61: 6 | T61: 7 | U61: 0 | V61: 0 | W61: 0 | X61: 0 | Y61: 0 | Z61: 0 | AA61: 3 | AB61: 11 | AC61: 0
A62: 6853 | B62: 1982 | C62: Master | D62: Single | E62: 75777 | F62: 0 | G62: 0 | H62: 2013-07-04 | I62: 12 | J62: 712 | K62: 26 | L62: 538 | M62: 69 | N62: 13 | O62: 80 | P62: 1 | Q62: 3 | R62: 6 | S62: 11 | T62: 1 | U62: 0 | V62: 1 | W62: 1 | X62: 0 | Y62: 0 | Z62: 0 | AA62: 3 | AB62: 11 | AC62: 1
A63: 3076 | B63: 1975 | C63: Graduation | D63: Together | E63: 66653 | F63: 1 | G63: 1 | H63: 2012-09-07 | I63: 18 | J63: 452 | K63: 18 | L63: 102 | M63: 16 | N63: 18 | O63: 6 | P63: 4 | Q63: 4 | R63: 2 | S63: 12 | T63: 3 | U63: 0 | V63: 0 | W63: 0 | X63: 0 | Y63: 0 | Z63: 0 | AA63: 3 | AB63: 11 | AC63: 0
A64: 1012 | B64: 1952 | C64: Graduation | D64: Single | E64: 61823 | F64: 0 | G64: 1 | H64: 2013-02-18 | I64: 26 | J64: 523 | K64: 7 | L64: 134 | M64: 37 | N64: 14 | O64: 169 | P64: 4 | Q64: 8 | R64: 2 | S64: 10 | T64: 7 | U64: 0 | V64: 0 | W64: 0 | X64: 0 | Y64: 0 | Z64: 0 | AA64: 3 | AB64: 11 | AC64: 0
A65: 6518 | B65: 1951 | C65: PhD | D65: Widow | E65: 67680 | F65: 0 | G65: 1 | H65: 2013-06-11 | I65: 8 | J65: 546 | K65: 0 | L65: 48 | M65: 0 | N65: 6 | O65: 6 | P65: 1 | Q65: 7 | R65: 3 | S65: 8 | T65: 5 | U65: 0 | V65: 0 | W65: 0 | X65: 0 | Y65: 0 | Z65: 0 | AA65: 3 | AB65: 11 | AC65: 0
A66: 4137 | B66: 1948 | C66: Graduation | D66: Together | E66: 70666 | F66: 0 | G66: 0 | H66: 2013-12-06 | I66: 29 | J66: 398 | K66: 40 | L66: 367 | M66: 119 | N66: 122 | O66: 30 | P66: 1 | Q66: 7 | R66: 4 | S66: 4 | T66: 4 | U66: 0 | V66: 0 | W66: 0 | X66: 0 | Y66: 0 | Z66: 0 | AA66: 3 | AB66: 11 | AC66: 0
A67: 8082 | B67: 1971 | C67: Graduation | D67: Married | E67: 25721 | F67: 1 | G67: 0 | H67: 2013-05-21 | I67: 75 | J67: 1 | K67: 3 | L67: 6 | M67: 3 | N67: 6 | O67: 15 | P67: 1 | Q67: 1 | R67: 1 | S67: 2 | T67: 7 | U67: 0 | V67: 0 | W67: 0 | X67: 0 | Y67: 0 | Z67: 0 | AA67: 3 | AB67: 11 | AC67: 1
A68: 1386 | B68: 1967 | C68: Graduation | D68: Together | E68: 32474 | F68: 1 | G68: 1 | H68: 2014-05-11 | I68: 0 | J68: 10 | K68: 0 | L68: 1 | M68: 0 | N68: 0 | O68: 0 | P68: 1 | Q68: 1 | R68: 0 | S68: 2 | T68: 7 | U68: 0 | V68: 0 | W68: 0 | X68: 0 | Y68: 0 | Z68: 0 | AA68: 3 | AB68: 11 | AC68: 0
A69: 9369 | B69: 1979 | C69: 2n Cycle | D69: Single | E69: 88194 | F69: 0 | G69: 1 | H69: 2014-03-19 | I69: 19 | J69: 688 | K69: 14 | L69: 309 | M69: 201 | N69: 24 | O69: 38 | P69: 1 | Q69: 11 | R69: 10 | S69: 10 | T69: 5 | U69: 1 | V69: 0 | W69: 0 | X69: 1 | Y69: 0 | Z69: 0 | AA69: 3 | AB69: 11 | AC69: 1
A70: 4477 | B70: 1958 | C70: Graduation | D70: Together | E70: 69096 | F70: 0 | G70: 1 | H70: 2013-09-27 | I70: 4 | J70: 247 | K70: 49 | L70: 159 | M70: 7 | N70: 82 | O70: 109 | P70: 1 | Q70: 5 | R70: 2 | S70: 10 | T70: 4 | U70: 0 | V70: 0 | W70: 0 | X70: 0 | Y70: 0 | Z70: 0 | AA70: 3 | AB70: 11 | AC70: 0
A71: 1357 | B71: 1970 | C71: Graduation | D71: Together | E71: 74854 | F71: 1 | G71: 2 | H71: 2013-04-08 | I71: 90 | J71: 856 | K71: 59 | L71: 487 | M71: 58 | N71: 29 | O71: 73 | P71: 7 | Q71: 2 | R71: 5 | S71: 5 | T71: 5 | U71: 0 | V71: 0 | W71: 0 | X71: 0 | Y71: 0 | Z71: 0 | AA71: 3 | AB71: 11 | AC71: 0
A72: 1402 | B72: 1954 | C72: Master | D72: Married | E72: 66991 | F72: 0 | G72: 0 | H72: 2012-09-11 | I72: 1 | J72: 496 | K72: 36 | L72: 460 | M72: 189 | N72: 60 | O72: 12 | P72: 3 | Q72: 4 | R72: 8 | S72: 6 | T72: 3 | U72: 0 | V72: 0 | W72: 0 | X72: 0 | Y72: 0 | Z72: 0 | AA72: 3 | AB72: 11 | AC72: 0
A73: 10629 | B73: 1973 | C73: 2n Cycle | D73: Married | F73: 1 | G73: 0 | H73: 2012-09-14 | I73: 25 | J73: 25 | K73: 3 | L73: 43 | M73: 17 | N73: 4 | O73: 17 | P73: 3 | Q73: 3 | R73: 0 | S73: 3 | T73: 8 | U73: 0 | V73: 0 | W73: 0 | X73: 0 | Y73: 0 | Z73: 0 | AA73: 3 | AB73: 11 | AC73: 0
A74: 6312 | B74: 1959 | C74: Graduation | D74: Married | E74: 65031 | F74: 0 | G74: 1 | H74: 2013-03-17 | I74: 29 | J74: 258 | K74: 107 | L74: 291 | M74: 84 | N74: 37 | O74: 86 | P74: 4 | Q74: 10 | R74: 3 | S74: 13 | T74: 7 | U74: 0 | V74: 0 | W74: 0 | X74: 0 | Y74: 0 | Z74: 0 | AA74: 3 | AB74: 11 | AC74: 0
A75: 8132 | B75: 1975 | C75: PhD | D75: Married | E75: 60631 | F75: 1 | G75: 1 | H75: 2013-04-05 | I75: 88 | J75: 565 | K75: 6 | L75: 65 | M75: 0 | N75: 6 | O75: 19 | P75: 5 | Q75: 9 | R75: 2 | S75: 8 | T75: 7 | U75: 0 | V75: 1 | W75: 0 | X75: 0 | Y75: 0 | Z75: 0 | AA75: 3 | AB75: 11 | AC75: 0
A76: 1050 | B76: 1952 | C76: Graduation | D76: Married | E76: 28332 | F76: 0 | G76: 0 | H76: 2014-04-30 | I76: 58 | J76: 14 | K76: 10 | L76: 13 | M76: 4 | N76: 15 | O76: 9 | P76: 1 | Q76: 2 | R76: 1 | S76: 4 | T76: 2 | U76: 0 | V76: 0 | W76: 0 | X76: 0 | Y76: 0 | Z76: 0 | AA76: 3 | AB76: 11 | AC76: 0
A77: 5846 | B77: 1977 | C77: Graduation | D77: Divorced | E77: 40246 | F77: 1 | G77: 0 | H77: 2012-12-19 | I77: 68 | J77: 2 | K77: 1 | L77: 6 | M77: 2 | N77: 1 | O77: 1 | P77: 1 | Q77: 1 | R77: 0 | S77: 2 | T77: 6 | U77: 0 | V77: 0 | W77: 0 | X77: 0 | Y77: 0 | Z77: 0 | AA77: 3 | AB77: 11 | AC77: 0
A78: 1859 | B78: 1972 | C78: Master | D78: Married | E78: 75251 | F78: 0 | G78: 0 | H78: 2012-08-27 | I78: 34 | J78: 721 | K78: 111 | L78: 925 | M78: 97 | N78: 18 | O78: 18 | P78: 1 | Q78: 7 | R78: 6 | S78: 5 | T78: 5 | U78: 0 | V78: 0 | W78: 0 | X78: 0 | Y78: 0 | Z78: 0 | AA78: 3 | AB78: 11 | AC78: 1
A79: 7503 | B79: 1976 | C79: Graduation | D79: Single | E79: 75825 | F79: 0 | G79: 0 | H79: 2012-10-12 | I79: 40 | J79: 1032 | K79: 105 | L79: 779 | M79: 137 | N79: 105 | O79: 51 | P79: 0 | Q79: 5 | R79: 8 | S79: 9 | T79: 4 | U79: 1 | V79: 0 | W79: 0 | X79: 0 | Y79: 0 | Z79: 0 | AA79: 3 | AB79: 11 | AC79: 1
A80: 10401 | B80: 1976 | C80: 2n Cycle | D80: Together | E80: 26326 | F80: 0 | G80: 0 | H80: 2013-09-04 | I80: 12 | J80: 1 | K80: 0 | L80: 5 | M80: 0 | N80: 3 | O80: 9 | P80: 1 | Q80: 0 | R80: 0 | S80: 3 | T80: 3 | U80: 0 | V80: 0 | W80: 0 | X80: 0 | Y80: 0 | Z80: 1 | AA80: 3 | AB80: 11 | AC80: 0
A81: 1618 | B81: 1965 | C81: Graduation | D81: Together | E81: 56046 | F81: 0 | G81: 0 | H81: 2013-01-02 | I81: 9 | J81: 577 | K81: 0 | L81: 64 | M81: 0 | N81: 0 | O81: 51 | P81: 2 | Q81: 10 | R81: 1 | S81: 8 | T81: 8 | U81: 1 | V81: 0 | W81: 0 | X81: 0 | Y81: 0 | Z81: 0 | AA81: 3 | AB81: 11 | AC81: 1
A82: 3332 | B82: 1985 | C82: Graduation | D82: Single | E82: 29760 | F82: 1 | G82: 0 | H82: 2012-08-29 | I82: 87 | J82: 64 | K82: 4 | L82: 68 | M82: 7 | N82: 5 | O82: 17 | P82: 4 | Q82: 3 | R82: 1 | S82: 4 | T82: 8 | U82: 0 | V82: 0 | W82: 0 | X82: 0 | Y82: 0 | Z82: 0 | AA82: 3 | AB82: 11 | AC82: 0
A83: 2261 | B83: 1969 | C83: Graduation | D83: Married | E83: 26304 | F83: 1 | G83: 0 | H83: 2013-06-23 | I83: 5 | J83: 4 | K83: 1 | L83: 5 | M83: 2 | N83: 0 | O83: 4 | P83: 1 | Q83: 1 | R83: 0 | S83: 2 | T83: 7 | U83: 0 | V83: 0 | W83: 0 | X83: 0 | Y83: 0 | Z83: 0 | AA83: 3 | AB83: 11 | AC83: 0
A84: 5346 | B84: 1973 | C84: 2n Cycle | D84: Married | E84: 23559 | F84: 1 | G84: 0 | H84: 2013-07-03 | I84: 87 | J84: 25 | K84: 5 | L84: 19 | M84: 7 | N84: 0 | O84: 23 | P84: 3 | Q84: 3 | R84: 0 | S84: 3 | T84: 7 | U84: 0 | V84: 0 | W84: 0 | X84: 0 | Y84: 0 | Z84: 0 | AA84: 3 | AB84: 11 | AC84: 0
A85: 4119 | B85: 1963 | C85: Master | D85: Together | E85: 38620 | F85: 0 | G85: 0 | H85: 2013-05-11 | I85: 56 | J85: 112 | K85: 17 | L85: 44 | M85: 34 | N85: 22 | O85: 89 | P85: 1 | Q85: 2 | R85: 5 | S85: 3 | T85: 3 | U85: 0 | V85: 0 | W85: 0 | X85: 0 | Y85: 0 | Z85: 0 | AA85: 3 | AB85: 11 | AC85: 0
... A91: 771 | B91: 1967 | C91: Graduation | D91: Together | E91: 54178 | F91: 0 | G91: 1 | H91: 2014-01-21 | I91: 79 | J91: 135 | K91: 9 | L91: 39 | M91: 4 | N91: 0 | O91: 7 | P91: 1 | Q91: 2 | R91: 2 | S91: 5 | T91: 2 | U91: 0 | V91: 0 | W91: 0 | X91: 0 | Y91: 0 | Z91: 0 | AA91: 3 | AB91: 11 | AC91: 0
A92: 8996 | B92: 1957 | C92: PhD | D92: Married | F92: 2 | G92: 1 | H92: 2012-11-19 | I92: 4 | J92: 230 | K92: 42 | L92: 192 | M92: 49 | N92: 37 | O92: 53 | P92: 12 | Q92: 7 | R92: 2 | S92: 8 | T92: 9 | U92: 0 | V92: 0 | W92: 0 | X92: 0 | Y92: 0 | Z92: 0 | AA92: 3 | AB92: 11 | AC92: 0
A93: 9235 | B93: 1957 | C93: Graduation | D93: Single | F93: 1 | G93: 1 | H93: 2014-05-27 | I93: 45 | J93: 7 | K93: 0 | L93: 8 | M93: 2 | N93: 0 | O93: 1 | P93: 1 | Q93: 1 | R93: 0 | S93: 2 | T93: 7 | U93: 0 | V93: 0 | W93: 0 | X93: 0 | Y93: 0 | Z93: 0 | AA93: 3 | AB93: 11 | AC93: 0
A94: 5798 | B94: 1973 | C94: Master | D94: Together | F94: 0 | G94: 0 | H94: 2013-11-23 | I94: 87 | J94: 445 | K94: 37 | L94: 359 | M94: 98 | N94: 28 | O94: 18 | P94: 1 | Q94: 2 | R94: 4 | S94: 8 | T94: 1 | U94: 0 | V94: 0 | W94: 0 | X94: 0 | Y94: 0 | Z94: 0 | AA94: 3 | AB94: 11 | AC94: 0
A95: 11178 | B95: 1972 | C95: Master | D95: Single | E95: 42394 | F95: 1 | G95: 0 | H95: 2014-03-23 | I95: 69 | J95: 15 | K95: 2 | L95: 10 | M95: 0 | N95: 1 | O95: 4 | P95: 1 | Q95: 1 | R95: 0 | S95: 3 | T95: 7 | U95: 0 | V95: 0 | W95: 0 | X95: 0 | Y95: 0 | Z95: 0 | AA95: 3 | AB95: 11 | AC95: 0
A96: 2230 | B96: 1970 | C96: PhD | D96: Married | E96: 23626 | F96: 1 | G96: 0 | H96: 2014-05-24 | I96: 84 | J96: 27 | K96: 2 | L96: 14 | M96: 0 | N96: 0 | O96: 0 | P96: 3 | Q96: 3 | R96: 1 | S96: 3 | T96: 5 | U96: 0 | V96: 0 | W96: 0 | X96: 0 | Y96: 0 | Z96: 0 | AA96: 3 | AB96: 11 | AC96: 0
A97: 7516 | B97: 1983 | C97: Graduation | D97: Married | E97: 30096 | F97: 1 | G97: 0 | H97: 2014-05-22 | I97: 30 | J97: 5 | K97: 3 | L97: 11 | M97: 12 | N97: 5 | O97: 9 | P97: 1 | Q97: 2 | R97: 0 | S97: 3 | T97: 6 | U97: 0 | V97: 0 | W97: 0 | X97: 0 | Y97: 0 | Z97: 0 | AA97: 3 | AB97: 11 | AC97: 0
A98: 7247 | B98: 1960 | C98: Graduation | D98: Widow | E98: 47916 | F98: 0 | G98: 1 | H98: 2012-11-22 | I98: 72 | J98: 505 | K98: 0 | L98: 26 | M98: 0 | N98: 0 | O98: 75 | P98: 5 | Q98: 7 | R98: 4 | S98: 6 | T98: 6 | U98: 0 | V98: 1 | W98: 0 | X98: 0 | Y98: 0 | Z98: 0 | AA98: 3 | AB98: 11 | AC98: 0
A99: 11100 | B99: 1972 | C99: Graduation | D99: Divorced | E99: 51813 | F99: 1 | G99: 1 | H99: 2013-04-11 | I99: 37 | J99: 51 | K99: 2 | L99: 7 | M99: 0 | N99: 1 | O99: 2 | P99: 2 | Q99: 2 | R99: 0 | S99: 3 | T99: 7 | U99: 0 | V99: 0 | W99: 0 | X99: 0 | Y99: 0 | Z99: 0 | AA99: 3 | AB99: 11 | AC99: 0
A100: 4646 | B100: 1951 | C100: 2n Cycle | D100: Married | E100: 78497 | F100: 0 | G100: 0 | H100: 2013-12-01 | I100: 44 | J100: 207 | K100: 26 | L100: 447 | M100: 75 | N100: 0 | O100: 223 | P100: 1 | Q100: 5 | R100: 7 | S100: 12 | T100: 2 | U100: 0 | V100: 0 | W100: 0 | X100: 1 | Y100: 0 | Z100: 0 | AA100: 3 | AB100: 11 | AC100: 0
A101: 3037 | B101: 1983 | C101: PhD | D101: Married | E101: 50150 | F101: 0 | G101: 0 | H101: 2013-06-20 | I101: 32 | J101: 135 | K101: 46 | L101: 92 | M101: 65 | N101: 61 | O101: 11 | P101: 2 | Q101: 5 | R101: 2 | S101: 7 | T101: 5 | U101: 0 | V101: 0 | W101: 0 | X101: 0 | Y101: 0 | Z101: 0 | AA101: 3 | AB101: 11 | AC101: 0
A102: 1473 | B102: 1960 | C102: 2n Cycle | D102: Single | E102: 47823 | F102: 0 | G102: 1 | H102: 2013-07-23 | I102: 0 | J102: 53 | K102: 1 | L102: 5 | M102: 2 | N102: 1 | O102: 10 | P102: 2 | Q102: 2 | R102: 0 | S102: 3 | T102: 8 | U102: 0 | V102: 0 | W102: 0 | X102: 0 | Y102: 0 | Z102: 0 | AA102: 3 | AB102: 11 | AC102: 0
A103: 1016 | B103: 1959 | C103: PhD | D103: Single | E103: 34554 | F103: 0 | G103: 1 | H103: 2014-03-30 | I103: 43 | J103: 41 | K103: 1 | L103: 6 | M103: 2 | N103: 0 | O103: 5 | P103: 2 | Q103: 2 | R103: 0 | S103: 3 | T103: 6 | U103: 0 | V103: 0 | W103: 0 | X103: 0 | Y103: 0 | Z103: 0 | AA103: 3 | AB103: 11 | AC103: 0
A104: 4518 | B104: 1979 | C104: Graduation | D104: Together | E104: 85693 | F104: 0 | G104: 1 | H104: 2013-04-20 | I104: 59 | J104: 386 | K104: 172 | L104: 183 | M104: 185 | N104: 132 | O104: 111 | P104: 2 | Q104: 9 | R104: 5 | S104: 11 | T104: 5 | U104: 0 | V104: 0 | W104: 0 | X104: 0 | Y104: 0 | Z104: 0 | AA104: 3 | AB104: 11 | AC104: 0
A105: 9370 | B105: 1945 | C105: PhD | D105: Married | E105: 65846 | F105: 0 | G105: 0 | H105: 2013-05-17 | I105: 68 | J105: 562 | K105: 81 | L105: 276 | M105: 80 | N105: 40 | O105: 81 | P105: 1 | Q105: 6 | R105: 3 | S105: 6 | T105: 4 | U105: 0 | V105: 0 | W105: 0 | X105: 0 | Y105: 0 | Z105: 0 | AA105: 3 | AB105: 11 | AC105: 0
A106: 8908 | B106: 1959 | C106: Graduation | D106: Married | E106: 87195 | F106: 0 | G106: 0 | H106: 2014-05-08 | I106: 35 | J106: 217 | K106: 76 | L106: 690 | M106: 50 | N106: 26 | O106: 38 | P106: 1 | Q106: 3 | R106: 11 | S106: 5 | T106: 1 | U106: 0 | V106: 0 | W106: 0 | X106: 0 | Y106: 0 | Z106: 0 | AA106: 3 | AB106: 11 | AC106: 1
... A129: 3381 | B129: 1953 | C129: Master | D129: Married | E129: 54348 | F129: 1 | G129: 1 | H129: 2014-06-08 | I129: 51 | J129: 70 | K129: 0 | L129: 16 | M129: 0 | N129: 0 | O129: 4 | P129: 2 | Q129: 2 | R129: 0 | S129: 4 | T129: 6 | U129: 0 | V129: 0 | W129: 0 | X129: 0 | Y129: 0 | Z129: 0 | AA129: 3 | AB129: 11 | AC129: 0
A130: 8268 | B130: 1961 | C130: PhD | D130: Married | F130: 0 | G130: 1 | H130: 2013-07-11 | I130: 23 | J130: 352 | K130: 0 | L130: 27 | M130: 10 | N130: 0 | O130: 15 | P130: 3 | Q130: 6 | R130: 1 | S130: 7 | T130: 6 | U130: 0 | V130: 0 | W130: 0 | X130: 0 | Y130: 0 | Z130: 0 | AA130: 3 | AB130: 11 | AC130: 0
A131: 11051 | B131: 1956 | C131: PhD | D131: Together | E131: 77376 | F131: 1 | G131: 1 | H131: 2014-05-10 | I131: 72 | J131: 492 | K131: 19 | L131: 110 | M131: 16 | N131: 12 | O131: 12 | P131: 4 | Q131: 6 | R131: 3 | S131: 10 | T131: 4 | U131: 0 | V131: 0 | W131: 0 | X131: 0 | Y131: 0 | Z131: 0 | AA131: 3 | AB131: 11 | AC131: 0
A132: 8026 | B132: 1952 | C132: Graduation | D132: Married | E132: 62998 | F132: 0 | G132: 1 | H132: 2013-09-30 | I132: 10 | J132: 120 | K132: 58 | L132: 73 | M132: 65 | N132: 89 | O132: 58 | P132: 5 | Q132: 5 | R132: 4 | S132: 5 | T132: 5 | U132: 0 | V132: 0 | W132: 0 | X132: 0 | Y132: 0 | Z132: 0 | AA132: 3 | AB132: 11 | AC132: 0
...

Sheet Data Cleaning
A1: ID | B1: Year_Birth | C1: Age | D1: Age_Group | E1: Education | F1: Marital_Status | G1: Income | H1: Income_Clean | I1: Income_Segment | J1: Income_Label | K1: Kidhome | L1: Teenhome | M1: HasChildren | N1: Dt_Customer | O1: Recency | P1: MntWines | Q1: MntFruits | R1: MntMeatProducts | S1: MntFishProducts | T1: MntSweetProducts | U1: MntGoldProds | V1: TotalSpend | W1: NumDealsPurchases | X1: NumWebPurchases | Y1: NumCatalogPurchases | Z1: NumStorePurchases | AA1: NumWebVisitsMonth | AB1: AcceptedCmp3 | AC1: AcceptedCmp4 | AD1: AcceptedCmp5 | AE1: AcceptedCmp1 | AF1: AcceptedCmp2 | AG1: TotalCampaigns | AH1: Complain | AI1: Response
A2: 5524 | B2: 1957 | C2: =2026-B2 -> 69 | D2: {=_xlfn.IFS(C2<36,"Young",C2<56,"Middle-aged",C2>=56,"Senior")} -> Senior | E2: Graduation | F2: Single | G2: 58138 | H2: =IF(G2=0,MEDIAN(Income),G2) -> 58138 | I2: {=_xlfn.IFS(H2<PERCENTILE(Income_Clean,0.33),"Low",H2<PERCENTILE(Income_Clean,0.67),"Medium",H2>PERCENTILE(Income_Clean,0.67),"High")} -> Medium | J2: =_xlfn.XLOOKUP(I2,$AK$3:$AK$5,$AL$3:$AL$5) -> Average Income | K2: 0 | L2: 0 | M2: =IF(K2+L2>0,"Yes","No") -> No | N2: 2012-09-04 | O2: 58 | P2: 635 | Q2: 88 | R2: 546 | S2: 172 | T2: 88 | U2: 88 | V2: =SUM(P2:U2) -> 1617 | W2: 3 | X2: 8 | Y2: 10 | Z2: 4 | AA2: 7 | AB2: 0 | AC2: 0 | AD2: 0 | AE2: 0 | AF2: 0 | AG2: =SUM(AB2:AF2) -> 0 | AH2: 0 | AI2: 1 | AK2: Income_Label | AN2: Data Quality Summary
A3: 2174 | B3: 1954 | C3: =2026-B3 -> 72 | D3: {=_xlfn.IFS(C3<36,"Young",C3<56,"Middle-aged",C3>=56,"Senior")} -> Senior | E3: Graduation | F3: Single | G3: 46344 | H3: =IF(G3=0,MEDIAN(Income),G3) -> 46344 | I3: {=_xlfn.IFS(H3<PERCENTILE(Income_Clean,0.33),"Low",H3<PERCENTILE(Income_Clean,0.67),"Medium",H3>PERCENTILE(Income_Clean,0.67),"High")} -> Medium | J3: =_xlfn.XLOOKUP(I3,$AK$3:$AK$5,$AL$3:$AL$5) -> Average Income | K3: 1 | L3: 1 | M3: =IF(K3+L3>0,"Yes","No") -> Yes | N3: 2014-03-08 | O3: 38 | P3: 11 | Q3: 1 | R3: 6 | S3: 2 | T3: 1 | U3: 6 | V3: =SUM(P3:U3) -> 27 | W3: 2 | X3: 1 | Y3: 1 | Z3: 2 | AA3: 5 | AB3: 0 | AC3: 0 | AD3: 0 | AE3: 0 | AF3: 0 | AG3: =SUM(AB3:AF3) -> 0 | AH3: 0 | AI3: 0 | AK3: Low | AL3: Below Average Income | AN3: Check | AO3: Result | AP3: Action
A4: 4141 | B4: 1965 | C4: =2026-B4 -> 61 | D4: {=_xlfn.IFS(C4<36,"Young",C4<56,"Middle-aged",C4>=56,"Senior")} -> Senior | E4: Graduation | F4: Together | G4: 71613 | H4: =IF(G4=0,MEDIAN(Income),G4) -> 71613 | I4: {=_xlfn.IFS(H4<PERCENTILE(Income_Clean,0.33),"Low",H4<PERCENTILE(Income_Clean,0.67),"Medium",H4>PERCENTILE(Income_Clean,0.67),"High")} -> High | J4: =_xlfn.XLOOKUP(I4,$AK$3:$AK$5,$AL$3:$AL$5) -> Above Average Income | K4: 0 | L4: 0 | M4: =IF(K4+L4>0,"Yes","No") -> No | N4: 2013-08-21 | O4: 26 | P4: 426 | Q4: 49 | R4: 127 | S4: 111 | T4: 21 | U4: 42 | V4: =SUM(P4:U4) -> 776 | W4: 1 | X4: 8 | Y4: 2 | Z4: 10 | AA4: 4 | AB4: 0 | AC4: 0 | AD4: 0 | AE4: 0 | AF4: 0 | AG4: =SUM(AB4:AF4) -> 0 | AH4: 0 | AI4: 0 | AK4: Medium | AL4: Average Income | AN4: Total Rows (before cleaning) | AO4: =COUNT('Raw Data'!A1:A2241) -> 2240
A5: 6182 | B5: 1984 | C5: =2026-B5 -> 42 | D5: {=_xlfn.IFS(C5<36,"Young",C5<56,"Middle-aged",C5>=56,"Senior")} -> Middle-aged | E5: Graduation | F5: Together | G5: 26646 | H5: =IF(G5=0,MEDIAN(Income),G5) -> 26646 | I5: {=_xlfn.IFS(H5<PERCENTILE(Income_Clean,0.33),"Low",H5<PERCENTILE(Income_Clean,0.67),"Medium",H5>PERCENTILE(Income_Clean,0.67),"High")} -> Low | J5: =_xlfn.XLOOKUP(I5,$AK$3:$AK$5,$AL$3:$AL$5) -> Below Average Income | K5: 1 | L5: 0 | M5: =IF(K5+L5>0,"Yes","No") -> Yes | N5: 2014-02-10 | O5: 26 | P5: 11 | Q5: 4 | R5: 20 | S5: 10 | T5: 3 | U5: 5 | V5: =SUM(P5:U5) -> 53 | W5: 2 | X5: 2 | Y5: 0 | Z5: 4 | AA5: 6 | AB5: 0 | AC5: 0 | AD5: 0 | AE5: 0 | AF5: 0 | AG5: =SUM(AB5:AF5) -> 0 | AH5: 0 | AI5: 0 | AK5: High | AL5: Above Average Income | AN5: Duplicate Rows | AO5: 0 | AP5: None needed
A6: 5324 | B6: 1981 | C6: =2026-B6 -> 45 | D6: {=_xlfn.IFS(C6<36,"Young",C6<56,"Middle-aged",C6>=56,"Senior")} -> Middle-aged | E6: PhD | F6: Married | G6: 58293 | H6: =IF(G6=0,MEDIAN(Income),G6) -> 58293 | I6: {=_xlfn.IFS(H6<PERCENTILE(Income_Clean,0.33),"Low",H6<PERCENTILE(Income_Clean,0.67),"Medium",H6>PERCENTILE(Income_Clean,0.67),"High")} -> Medium | J6: =_xlfn.XLOOKUP(I6,$AK$3:$AK$5,$AL$3:$AL$5) -> Average Income | K6: 1 | L6: 0 | M6: =IF(K6+L6>0,"Yes","No") -> Yes | N6: 2014-01-19 | O6: 94 | P6: 173 | Q6: 43 | R6: 118 | S6: 46 | T6: 27 | U6: 15 | V6: =SUM(P6:U6) -> 422 | W6: 5 | X6: 5 | Y6: 3 | Z6: 6 | AA6: 5 | AB6: 0 | AC6: 0 | AD6: 0 | AE6: 0 | AF6: 0 | AG6: =SUM(AB6:AF6) -> 0 | AH6: 0 | AI6: 0 | AN6: Missing Income values | AO6: =COUNTBLANK('Raw Data'!E1:E2241) -> 24 | AP6: Filled with median
A7: 7446 | B7: 1967 | C7: =2026-B7 -> 59 | D7: {=_xlfn.IFS(C7<36,"Young",C7<56,"Middle-aged",C7>=56,"Senior")} -> Senior | E7: Master | F7: Together | G7: 62513 | H7: =IF(G7=0,MEDIAN(Income),G7) -> 62513 | I7: {=_xlfn.IFS(H7<PERCENTILE(Income_Clean,0.33),"Low",H7<PERCENTILE(Income_Clean,0.67),"Medium",H7>PERCENTILE(Income_Clean,0.67),"High")} -> Medium | J7: =_xlfn.XLOOKUP(I7,$AK$3:$AK$5,$AL$3:$AL$5) -> Average Income | K7: 0 | L7: 1 | M7: =IF(K7+L7>0,"Yes","No") -> Yes | N7: 2013-09-09 | O7: 16 | P7: 520 | Q7: 42 | R7: 98 | S7: 0 | T7: 42 | U7: 14 | V7: =SUM(P7:U7) -> 716 | W7: 2 | X7: 6 | Y7: 4 | Z7: 10 | AA7: 6 | AB7: 0 | AC7: 0 | AD7: 0 | AE7: 0 | AF7: 0 | AG7: =SUM(AB7:AF7) -> 0 | AH7: 0 | AI7: 0 | AN7: Age outliers removed | AO7: 3 | AP7: Rows deleted
A8: 965 | B8: 1971 | C8: =2026-B8 -> 55 | D8: {=_xlfn.IFS(C8<36,"Young",C8<56,"Middle-aged",C8>=56,"Senior")} -> Middle-aged | E8: Graduation | F8: Divorced | G8: 55635 | H8: =IF(G8=0,MEDIAN(Income),G8) -> 55635 | I8: {=_xlfn.IFS(H8<PERCENTILE(Income_Clean,0.33),"Low",H8<PERCENTILE(Income_Clean,0.67),"Medium",H8>PERCENTILE(Income_Clean,0.67),"High")} -> Medium | J8: =_xlfn.XLOOKUP(I8,$AK$3:$AK$5,$AL$3:$AL$5) -> Average Income | K8: 0 | L8: 1 | M8: =IF(K8+L8>0,"Yes","No") -> Yes | N8: 2012-11-13 | O8: 34 | P8: 235 | Q8: 65 | R8: 164 | S8: 50 | T8: 49 | U8: 27 | V8: =SUM(P8:U8) -> 590 | W8: 4 | X8: 7 | Y8: 3 | Z8: 7 | AA8: 6 | AB8: 0 | AC8: 0 | AD8: 0 | AE8: 0 | AF8: 0 | AG8: =SUM(AB8:AF8) -> 0 | AH8: 0 | AI8: 0 | AN8: Income outliers removed | AO8: 1 | AP8: Rows deleted
A9: 6177 | B9: 1985 | C9: =2026-B9 -> 41 | D9: {=_xlfn.IFS(C9<36,"Young",C9<56,"Middle-aged",C9>=56,"Senior")} -> Middle-aged | E9: PhD | F9: Married | G9: 33454 | H9: =IF(G9=0,MEDIAN(Income),G9) -> 33454 | I9: {=_xlfn.IFS(H9<PERCENTILE(Income_Clean,0.33),"Low",H9<PERCENTILE(Income_Clean,0.67),"Medium",H9>PERCENTILE(Income_Clean,0.67),"High")} -> Low | J9: =_xlfn.XLOOKUP(I9,$AK$3:$AK$5,$AL$3:$AL$5) -> Below Average Income | K9: 1 | L9: 0 | M9: =IF(K9+L9>0,"Yes","No") -> Yes | N9: 2013-05-08 | O9: 32 | P9: 76 | Q9: 10 | R9: 56 | S9: 3 | T9: 1 | U9: 23 | V9: =SUM(P9:U9) -> 169 | W9: 2 | X9: 4 | Y9: 0 | Z9: 4 | AA9: 8 | AB9: 0 | AC9: 0 | AD9: 0 | AE9: 0 | AF9: 0 | AG9: =SUM(AB9:AF9) -> 0 | AH9: 0 | AI9: 0 | AN9: Marital_Status cleaned | AO9: 7 values | AP9: Recategorized
A10: 4855 | B10: 1974 | C10: =2026-B10 -> 52 | D10: {=_xlfn.IFS(C10<36,"Young",C10<56,"Middle-aged",C10>=56,"Senior")} -> Middle-aged | E10: PhD | F10: Together | G10: 30351 | H10: =IF(G10=0,MEDIAN(Income),G10) -> 30351 | I10: {=_xlfn.IFS(H10<PERCENTILE(Income_Clean,0.33),"Low",H10<PERCENTILE(Income_Clean,0.67),"Medium",H10>PERCENTILE(Income_Clean,0.67),"High")} -> Low | J10: =_xlfn.XLOOKUP(I10,$AK$3:$AK$5,$AL$3:$AL$5) -> Below Average Income | K10: 1 | L10: 0 | M10: =IF(K10+L10>0,"Yes","No") -> Yes | N10: 2013-06-06 | O10: 19 | P10: 14 | Q10: 0 | R10: 24 | S10: 3 | T10: 3 | U10: 2 | V10: =SUM(P10:U10) -> 46 | W10: 1 | X10: 3 | Y10: 0 | Z10: 2 | AA10: 9 | AB10: 0 | AC10: 0 | AD10: 0 | AE10: 0 | AF10: 0 | AG10: =SUM(AB10:AF10) -> 0 | AH10: 0 | AI10: 1 | AN10: Final Rows | AO10: =COUNT(A1:A2237) -> 2236 | AP10: Ready for analysis
A11: 5899 | B11: 1950 | C11: =2026-B11 -> 76 | D11: {=_xlfn.IFS(C11<36,"Young",C11<56,"Middle-aged",C11>=56,"Senior")} -> Senior | E11: PhD | F11: Together | G11: 5648 | H11: =IF(G11=0,MEDIAN(Income),G11) -> 5648 | I11: {=_xlfn.IFS(H11<PERCENTILE(Income_Clean,0.33),"Low",H11<PERCENTILE(Income_Clean,0.67),"Medium",H11>PERCENTILE(Income_Clean,0.67),"High")} -> Low | J11: =_xlfn.XLOOKUP(I11,$AK$3:$AK$5,$AL$3:$AL$5) -> Below Average Income | K11: 1 | L11: 1 | M11: =IF(K11+L11>0,"Yes","No") -> Yes | N11: 2014-03-13 | O11: 68 | P11: 28 | Q11: 0 | R11: 6 | S11: 1 | T11: 1 | U11: 13 | V11: =SUM(P11:U11) -> 49 | W11: 1 | X11: 1 | Y11: 0 | Z11: 0 | AA11: 20 | AB11: 1 | AC11: 0 | AD11: 0 | AE11: 0 | AF11: 0 | AG11: =SUM(AB11:AF11) -> 1 | AH11: 0 | AI11: 0
A12: 1994 | B12: 1983 | C12: =2026-B12 -> 43 | D12: {=_xlfn.IFS(C12<36,"Young",C12<56,"Middle-aged",C12>=56,"Senior")} -> Middle-aged | E12: Graduation | F12: Married | H12: =IF(G12=0,MEDIAN(Income),G12) -> 51371 | I12: {=_xlfn.IFS(H12<PERCENTILE(Income_Clean,0.33),"Low",H12<PERCENTILE(Income_Clean,0.67),"Medium",H12>PERCENTILE(Income_Clean,0.67),"High")} -> Medium | J12: =_xlfn.XLOOKUP(I12,$AK$3:$AK$5,$AL$3:$AL$5) -> Average Income | K12: 1 | L12: 0 | M12: =IF(K12+L12>0,"Yes","No") -> Yes | N12: 2013-11-15 | O12: 11 | P12: 5 | Q12: 5 | R12: 6 | S12: 0 | T12: 2 | U12: 1 | V12: =SUM(P12:U12) -> 19 | W12: 1 | X12: 1 | Y12: 0 | Z12: 2 | AA12: 7 | AB12: 0 | AC12: 0 | AD12: 0 | AE12: 0 | AF12: 0 | AG12: =SUM(AB12:AF12) -> 0 | AH12: 0 | AI12: 0
A13: 387 | B13: 1976 | C13: =2026-B13 -> 50 | D13: {=_xlfn.IFS(C13<36,"Young",C13<56,"Middle-aged",C13>=56,"Senior")} -> Middle-aged | E13: Basic | F13: Married | G13: 7500 | H13: =IF(G13=0,MEDIAN(Income),G13) -> 7500 | I13: {=_xlfn.IFS(H13<PERCENTILE(Income_Clean,0.33),"Low",H13<PERCENTILE(Income_Clean,0.67),"Medium",H13>PERCENTILE(Income_Clean,0.67),"High")} -> Low | J13: =_xlfn.XLOOKUP(I13,$AK$3:$AK$5,$AL$3:$AL$5) -> Below Average Income | K13: 0 | L13: 0 | M13: =IF(K13+L13>0,"Yes","No") -> No | N13: 2012-11-13 | O13: 59 | P13: 6 | Q13: 16 | R13: 11 | S13: 11 | T13: 1 | U13: 16 | V13: =SUM(P13:U13) -> 61 | W13: 1 | X13: 2 | Y13: 0 | Z13: 3 | AA13: 8 | AB13: 0 | AC13: 0 | AD13: 0 | AE13: 0 | AF13: 0 | AG13: =SUM(AB13:AF13) -> 0 | AH13: 0 | AI13: 0
A14: 2125 | B14: 1959 | C14: =2026-B14 -> 67 | D14: {=_xlfn.IFS(C14<36,"Young",C14<56,"Middle-aged",C14>=56,"Senior")} -> Senior | E14: Graduation | F14: Divorced | G14: 63033 | H14: =IF(G14=0,MEDIAN(Income),G14) -> 63033 | I14: {=_xlfn.IFS(H14<PERCENTILE(Income_Clean,0.33),"Low",H14<PERCENTILE(Income_Clean,0.67),"Medium",H14>PERCENTILE(Income_Clean,0.67),"High")} -> High | J14: =_xlfn.XLOOKUP(I14,$AK$3:$AK$5,$AL$3:$AL$5) -> Above Average Income | K14: 0 | L14: 0 | M14: =IF(K14+L14>0,"Yes","No") -> No | N14: 2013-11-15 | O14: 82 | P14: 194 | Q14: 61 | R14: 480 | S14: 225 | T14: 112 | U14: 30 | V14: =SUM(P14:U14) -> 1102 | W14: 1 | X14: 3 | Y14: 4 | Z14: 8 | AA14: 2 | AB14: 0 | AC14: 0 | AD14: 0 | AE14: 0 | AF14: 0 | AG14: =SUM(AB14:AF14) -> 0 | AH14: 0 | AI14: 0
A15: 8180 | B15: 1952 | C15: =2026-B15 -> 74 | D15: {=_xlfn.IFS(C15<36,"Young",C15<56,"Middle-aged",C15>=56,"Senior")} -> Senior | E15: Master | F15: Divorced | G15: 59354 | H15: =IF(G15=0,MEDIAN(Income),G15) -> 59354 | I15: {=_xlfn.IFS(H15<PERCENTILE(Income_Clean,0.33),"Low",H15<PERCENTILE(Income_Clean,0.67),"Medium",H15>PERCENTILE(Income_Clean,0.67),"High")} -> Medium | J15: =_xlfn.XLOOKUP(I15,$AK$3:$AK$5,$AL$3:$AL$5) -> Average Income | K15: 1 | L15: 1 | M15: =IF(K15+L15>0,"Yes","No") -> Yes | N15: 2013-11-15 | O15: 53 | P15: 233 | Q15: 2 | R15: 53 | S15: 3 | T15: 5 | U15: 14 | V15: =SUM(P15:U15) -> 310 | W15: 3 | X15: 6 | Y15: 1 | Z15: 5 | AA15: 6 | AB15: 0 | AC15: 0 | AD15: 0 | AE15: 0 | AF15: 0 | AG15: =SUM(AB15:AF15) -> 0 | AH15: 0 | AI15: 0
A16: 2569 | B16: 1987 | C16: =2026-B16 -> 39 | D16: {=_xlfn.IFS(C16<36,"Young",C16<56,"Middle-aged",C16>=56,"Senior")} -> Middle-aged | E16: Graduation | F16: Married | G16: 17323 | H16: =IF(G16=0,MEDIAN(Income),G16) -> 17323 | I16: {=_xlfn.IFS(H16<PERCENTILE(Income_Clean,0.33),"Low",H16<PERCENTILE(Income_Clean,0.67),"Medium",H16>PERCENTILE(Income_Clean,0.67),"High")} -> Low | J16: =_xlfn.XLOOKUP(I16,$AK$3:$AK$5,$AL$3:$AL$5) -> Below Average Income | K16: 0 | L16: 0 | M16: =IF(K16+L16>0,"Yes","No") -> No | N16: 2012-10-10 | O16: 38 | P16: 3 | Q16: 14 | R16: 17 | S16: 6 | T16: 1 | U16: 5 | V16: =SUM(P16:U16) -> 46 | W16: 1 | X16: 1 | Y16: 0 | Z16: 3 | AA16: 8 | AB16: 0 | AC16: 0 | AD16: 0 | AE16: 0 | AF16: 0 | AG16: =SUM(AB16:AF16) -> 0 | AH16: 0 | AI16: 0
A17: 2114 | B17: 1946 | C17: =2026-B17 -> 80 | D17: {=_xlfn.IFS(C17<36,"Young",C17<56,"Middle-aged",C17>=56,"Senior")} -> Senior | E17: PhD | F17: Single | G17: 82800 | H17: =IF(G17=0,MEDIAN(Income),G17) -> 82800 | I17: {=_xlfn.IFS(H17<PERCENTILE(Income_Clean,0.33),"Low",H17<PERCENTILE(Income_Clean,0.67),"Medium",H17>PERCENTILE(Income_Clean,0.67),"High")} -> High | J17: =_xlfn.XLOOKUP(I17,$AK$3:$AK$5,$AL$3:$AL$5) -> Above Average Income | K17: 0 | L17: 0 | M17: =IF(K17+L17>0,"Yes","No") -> No | N17: 2012-11-24 | O17: 23 | P17: 1006 | Q17: 22 | R17: 115 | S17: 59 | T17: 68 | U17: 45 | V17: =SUM(P17:U17) -> 1315 | W17: 1 | X17: 7 | Y17: 6 | Z17: 12 | AA17: 3 | AB17: 0 | AC17: 0 | AD17: 1 | AE17: 1 | AF17: 0 | AG17: =SUM(AB17:AF17) -> 2 | AH17: 0 | AI17: 1
A18: 9736 | B18: 1980 | C18: =2026-B18 -> 46 | D18: {=_xlfn.IFS(C18<36,"Young",C18<56,"Middle-aged",C18>=56,"Senior")} -> Middle-aged | E18: Graduation | F18: Married | G18: 41850 | H18: =IF(G18=0,MEDIAN(Income),G18) -> 41850 | I18: {=_xlfn.IFS(H18<PERCENTILE(Income_Clean,0.33),"Low",H18<PERCENTILE(Income_Clean,0.67),"Medium",H18>PERCENTILE(Income_Clean,0.67),"High")} -> Medium | J18: =_xlfn.XLOOKUP(I18,$AK$3:$AK$5,$AL$3:$AL$5) -> Average Income | K18: 1 | L18: 1 | M18: =IF(K18+L18>0,"Yes","No") -> Yes | N18: 2012-12-24 | O18: 51 | P18: 53 | Q18: 5 | R18: 19 | S18: 2 | T18: 13 | U18: 4 | V18: =SUM(P18:U18) -> 96 | W18: 3 | X18: 3 | Y18: 0 | Z18: 3 | AA18: 8 | AB18: 0 | AC18: 0 | AD18: 0 | AE18: 0 | AF18: 0 | AG18: =SUM(AB18:AF18) -> 0 | AH18: 0 | AI18: 0
A19: 4939 | B19: 1946 | C19: =2026-B19 -> 80 | D19: {=_xlfn.IFS(C19<36,"Young",C19<56,"Middle-aged",C19>=56,"Senior")} -> Senior | E19: Graduation | F19: Together | G19: 37760 | H19: =IF(G19=0,MEDIAN(Income),G19) -> 37760 | I19: {=_xlfn.IFS(H19<PERCENTILE(Income_Clean,0.33),"Low",H19<PERCENTILE(Income_Clean,0.67),"Medium",H19>PERCENTILE(Income_Clean,0.67),"High")} -> Low | J19: =_xlfn.XLOOKUP(I19,$AK$3:$AK$5,$AL$3:$AL$5) -> Below Average Income | K19: 0 | L19: 0 | M19: =IF(K19+L19>0,"Yes","No") -> No | N19: 2012-08-31 | O19: 20 | P19: 84 | Q19: 5 | R19: 38 | S19: 150 | T19: 12 | U19: 28 | V19: =SUM(P19:U19) -> 317 | W19: 2 | X19: 4 | Y19: 1 | Z19: 6 | AA19: 7 | AB19: 0 | AC19: 0 | AD19: 0 | AE19: 0 | AF19: 0 | AG19: =SUM(AB19:AF19) -> 0 | AH19: 0 | AI19: 0
A20: 6565 | B20: 1949 | C20: =2026-B20 -> 77 | D20: {=_xlfn.IFS(C20<36,"Young",C20<56,"Middle-aged",C20>=56,"Senior")} -> Senior | E20: Master | F20: Married | G20: 76995 | H20: =IF(G20=0,MEDIAN(Income),G20) -> 76995 | I20: {=_xlfn.IFS(H20<PERCENTILE(Income_Clean,0.33),"Low",H20<PERCENTILE(Income_Clean,0.67),"Medium",H20>PERCENTILE(Income_Clean,0.67),"High")} -> High | J20: =_xlfn.XLOOKUP(I20,$AK$3:$AK$5,$AL$3:$AL$5) -> Above Average Income | K20: 0 | L20: 1 | M20: =IF(K20+L20>0,"Yes","No") -> Yes | N20: 2013-03-28 | O20: 91 | P20: 1012 | Q20: 80 | R20: 498 | S20: 0 | T20: 16 | U20: 176 | V20: =SUM(P20:U20) -> 1782 | W20: 2 | X20: 11 | Y20: 4 | Z20: 9 | AA20: 5 | AB20: 0 | AC20: 0 | AD20: 0 | AE20: 1 | AF20: 0 | AG20: =SUM(AB20:AF20) -> 1 | AH20: 0 | AI20: 0
A21: 2278 | B21: 1985 | C21: =2026-B21 -> 41 | D21: {=_xlfn.IFS(C21<36,"Young",C21<56,"Middle-aged",C21>=56,"Senior")} -> Middle-aged | E21: 2n Cycle | F21: Single | G21: 33812 | H21: =IF(G21=0,MEDIAN(Income),G21) -> 33812 | I21: {=_xlfn.IFS(H21<PERCENTILE(Income_Clean,0.33),"Low",H21<PERCENTILE(Income_Clean,0.67),"Medium",H21>PERCENTILE(Income_Clean,0.67),"High")} -> Low | J21: =_xlfn.XLOOKUP(I21,$AK$3:$AK$5,$AL$3:$AL$5) -> Below Average Income | K21: 1 | L21: 0 | M21: =IF(K21+L21>0,"Yes","No") -> Yes | N21: 2012-11-03 | O21: 86 | P21: 4 | Q21: 17 | R21: 19 | S21: 30 | T21: 24 | U21: 39 | V21: =SUM(P21:U21) -> 133 | W21: 2 | X21: 2 | Y21: 1 | Z21: 3 | AA21: 6 | AB21: 0 | AC21: 0 | AD21: 0 | AE21: 0 | AF21: 0 | AG21: =SUM(AB21:AF21) -> 0 | AH21: 0 | AI21: 0
A22: 9360 | B22: 1982 | C22: =2026-B22 -> 44 | D22: {=_xlfn.IFS(C22<36,"Young",C22<56,"Middle-aged",C22>=56,"Senior")} -> Middle-aged | E22: Graduation | F22: Married | G22: 37040 | H22: =IF(G22=0,MEDIAN(Income),G22) -> 37040 | I22: {=_xlfn.IFS(H22<PERCENTILE(Income_Clean,0.33),"Low",H22<PERCENTILE(Income_Clean,0.67),"Medium",H22>PERCENTILE(Income_Clean,0.67),"High")} -> Low | J22: =_xlfn.XLOOKUP(I22,$AK$3:$AK$5,$AL$3:$AL$5) -> Below Average Income | K22: 0 | L22: 0 | M22: =IF(K22+L22>0,"Yes","No") -> No | N22: 2012-08-08 | O22: 41 | P22: 86 | Q22: 2 | R22: 73 | S22: 69 | T22: 38 | U22: 48 | V22: =SUM(P22:U22) -> 316 | W22: 1 | X22: 4 | Y22: 2 | Z22: 5 | AA22: 8 | AB22: 0 | AC22: 0 | AD22: 0 | AE22: 0 | AF22: 0 | AG22: =SUM(AB22:AF22) -> 0 | AH22: 0 | AI22: 0
A23: 5376 | B23: 1979 | C23: =2026-B23 -> 47 | D23: {=_xlfn.IFS(C23<36,"Young",C23<56,"Middle-aged",C23>=56,"Senior")} -> Middle-aged | E23: Graduation | F23: Married | G23: 2447 | H23: =IF(G23=0,MEDIAN(Income),G23) -> 2447 | I23: {=_xlfn.IFS(H23<PERCENTILE(Income_Clean,0.33),"Low",H23<PERCENTILE(Income_Clean,0.67),"Medium",H23>PERCENTILE(Income_Clean,0.67),"High")} -> Low | J23: =_xlfn.XLOOKUP(I23,$AK$3:$AK$5,$AL$3:$AL$5) -> Below Average Income | K23: 1 | L23: 0 | M23: =IF(K23+L23>0,"Yes","No") -> Yes | N23: 2013-01-06 | O23: 42 | P23: 1 | Q23: 1 | R23: 1725 | S23: 1 | T23: 1 | U23: 1 | V23: =SUM(P23:U23) -> 1730 | W23: 15 | X23: 0 | Y23: 28 | Z23: 0 | AA23: 1 | AB23: 0 | AC23: 0 | AD23: 0 | AE23: 0 | AF23: 0 | AG23: =SUM(AB23:AF23) -> 0 | AH23: 0 | AI23: 0
A24: 1993 | B24: 1949 | C24: =2026-B24 -> 77 | D24: {=_xlfn.IFS(C24<36,"Young",C24<56,"Middle-aged",C24>=56,"Senior")} -> Senior | E24: PhD | F24: Married | G24: 58607 | H24: =IF(G24=0,MEDIAN(Income),G24) -> 58607 | I24: {=_xlfn.IFS(H24<PERCENTILE(Income_Clean,0.33),"Low",H24<PERCENTILE(Income_Clean,0.67),"Medium",H24>PERCENTILE(Income_Clean,0.67),"High")} -> Medium | J24: =_xlfn.XLOOKUP(I24,$AK$3:$AK$5,$AL$3:$AL$5) -> Average Income | K24: 0 | L24: 1 | M24: =IF(K24+L24>0,"Yes","No") -> Yes | N24: 2012-12-23 | O24: 63 | P24: 867 | Q24: 0 | R24: 86 | S24: 0 | T24: 0 | U24: 19 | V24: =SUM(P24:U24) -> 972 | W24: 3 | X24: 2 | Y24: 3 | Z24: 9 | AA24: 8 | AB24: 0 | AC24: 1 | AD24: 0 | AE24: 0 | AF24: 0 | AG24: =SUM(AB24:AF24) -> 1 | AH24: 0 | AI24: 0
... A28: 2404 | B28: 1976 | C28: =2026-B28 -> 50 | D28: {=_xlfn.IFS(C28<36,"Young",C28<56,"Middle-aged",C28>=56,"Senior")} -> Middle-aged | E28: Graduation | F28: Married | G28: 53359 | H28: =IF(G28=0,MEDIAN(Income),G28) -> 53359 | I28: {=_xlfn.IFS(H28<PERCENTILE(Income_Clean,0.33),"Low",H28<PERCENTILE(Income_Clean,0.67),"Medium",H28>PERCENTILE(Income_Clean,0.67),"High")} -> Medium | J28: =_xlfn.XLOOKUP(I28,$AK$3:$AK$5,$AL$3:$AL$5) -> Average Income | K28: 1 | L28: 1 | M28: =IF(K28+L28>0,"Yes","No") -> Yes | N28: 2013-05-27 | O28: 4 | P28: 173 | Q28: 4 | R28: 30 | S28: 3 | T28: 6 | U28: 41 | V28: =SUM(P28:U28) -> 257 | W28: 4 | X28: 5 | Y28: 1 | Z28: 4 | AA28: 7 | AB28: 0 | AC28: 0 | AD28: 0 | AE28: 0 | AF28: 0 | AG28: =SUM(AB28:AF28) -> 0 | AH28: 0 | AI28: 0
A29: 5255 | B29: 1986 | C29: =2026-B29 -> 40 | D29: {=_xlfn.IFS(C29<36,"Young",C29<56,"Middle-aged",C29>=56,"Senior")} -> Middle-aged | E29: Graduation | F29: Single | H29: =IF(G29=0,MEDIAN(Income),G29) -> 51371 | I29: {=_xlfn.IFS(H29<PERCENTILE(Income_Clean,0.33),"Low",H29<PERCENTILE(Income_Clean,0.67),"Medium",H29>PERCENTILE(Income_Clean,0.67),"High")} -> Medium | J29: =_xlfn.XLOOKUP(I29,$AK$3:$AK$5,$AL$3:$AL$5) -> Average Income | K29: 1 | L29: 0 | M29: =IF(K29+L29>0,"Yes","No") -> Yes | N29: 2013-02-20 | O29: 19 | P29: 5 | Q29: 1 | R29: 3 | S29: 3 | T29: 263 | U29: 362 | V29: =SUM(P29:U29) -> 637 | W29: 0 | X29: 27 | Y29: 0 | Z29: 0 | AA29: 1 | AB29: 0 | AC29: 0 | AD29: 0 | AE29: 0 | AF29: 0 | AG29: =SUM(AB29:AF29) -> 0 | AH29: 0 | AI29: 0
A30: 9422 | B30: 1989 | C30: =2026-B30 -> 37 | D30: {=_xlfn.IFS(C30<36,"Young",C30<56,"Middle-aged",C30>=56,"Senior")} -> Middle-aged | E30: Graduation | F30: Married | G30: 38360 | H30: =IF(G30=0,MEDIAN(Income),G30) -> 38360 | I30: {=_xlfn.IFS(H30<PERCENTILE(Income_Clean,0.33),"Low",H30<PERCENTILE(Income_Clean,0.67),"Medium",H30>PERCENTILE(Income_Clean,0.67),"High")} -> Low | J30: =_xlfn.XLOOKUP(I30,$AK$3:$AK$5,$AL$3:$AL$5) -> Below Average Income | K30: 1 | L30: 0 | M30: =IF(K30+L30>0,"Yes","No") -> Yes | N30: 2013-05-31 | O30: 26 | P30: 36 | Q30: 2 | R30: 42 | S30: 20 | T30: 21 | U30: 10 | V30: =SUM(P30:U30) -> 131 | W30: 2 | X30: 2 | Y30: 1 | Z30: 4 | AA30: 3 | AB30: 0 | AC30: 0 | AD30: 0 | AE30: 0 | AF30: 0 | AG30: =SUM(AB30:AF30) -> 0 | AH30: 0 | AI30: 0
A31: 1966 | B31: 1965 | C31: =2026-B31 -> 61 | D31: {=_xlfn.IFS(C31<36,"Young",C31<56,"Middle-aged",C31>=56,"Senior")} -> Senior | E31: PhD | F31: Married | G31: 84618 | H31: =IF(G31=0,MEDIAN(Income),G31) -> 84618 | I31: {=_xlfn.IFS(H31<PERCENTILE(Income_Clean,0.33),"Low",H31<PERCENTILE(Income_Clean,0.67),"Medium",H31>PERCENTILE(Income_Clean,0.67),"High")} -> High | J31: =_xlfn.XLOOKUP(I31,$AK$3:$AK$5,$AL$3:$AL$5) -> Above Average Income | K31: 0 | L31: 0 | M31: =IF(K31+L31>0,"Yes","No") -> No | N31: 2013-11-22 | O31: 96 | P31: 684 | Q31: 100 | R31: 801 | S31: 21 | T31: 66 | U31: 0 | V31: =SUM(P31:U31) -> 1672 | W31: 1 | X31: 6 | Y31: 9 | Z31: 10 | AA31: 2 | AB31: 0 | AC31: 0 | AD31: 1 | AE31: 0 | AF31: 0 | AG31: =SUM(AB31:AF31) -> 1 | AH31: 0 | AI31: 0
A32: 6864 | B32: 1989 | C32: =2026-B32 -> 37 | D32: {=_xlfn.IFS(C32<36,"Young",C32<56,"Middle-aged",C32>=56,"Senior")} -> Middle-aged | E32: Master | F32: Divorced | G32: 10979 | H32: =IF(G32=0,MEDIAN(Income),G32) -> 10979 | I32: {=_xlfn.IFS(H32<PERCENTILE(Income_Clean,0.33),"Low",H32<PERCENTILE(Income_Clean,0.67),"Medium",H32>PERCENTILE(Income_Clean,0.67),"High")} -> Low | J32: =_xlfn.XLOOKUP(I32,$AK$3:$AK$5,$AL$3:$AL$5) -> Below Average Income | K32: 0 | L32: 0 | M32: =IF(K32+L32>0,"Yes","No") -> No | N32: 2014-05-22 | O32: 34 | P32: 8 | Q32: 4 | R32: 10 | S32: 2 | T32: 2 | U32: 4 | V32: =SUM(P32:U32) -> 30 | W32: 2 | X32: 3 | Y32: 0 | Z32: 3 | AA32: 5 | AB32: 0 | AC32: 0 | AD32: 0 | AE32: 0 | AF32: 0 | AG32: =SUM(AB32:AF32) -> 0 | AH32: 0 | AI32: 0
A33: 3033 | B33: 1963 | C33: =2026-B33 -> 63 | D33: {=_xlfn.IFS(C33<36,"Young",C33<56,"Middle-aged",C33>=56,"Senior")} -> Senior | E33: Master | F33: Together | G33: 38620 | H33: =IF(G33=0,MEDIAN(Income),G33) -> 38620 | I33: {=_xlfn.IFS(H33<PERCENTILE(Income_Clean,0.33),"Low",H33<PERCENTILE(Income_Clean,0.67),"Medium",H33>PERCENTILE(Income_Clean,0.67),"High")} -> Low | J33: =_xlfn.XLOOKUP(I33,$AK$3:$AK$5,$AL$3:$AL$5) -> Below Average Income | K33: 0 | L33: 0 | M33: =IF(K33+L33>0,"Yes","No") -> No | N33: 2013-05-11 | O33: 56 | P33: 112 | Q33: 17 | R33: 44 | S33: 34 | T33: 22 | U33: 89 | V33: =SUM(P33:U33) -> 318 | W33: 1 | X33: 2 | Y33: 5 | Z33: 3 | AA33: 3 | AB33: 0 | AC33: 0 | AD33: 0 | AE33: 0 | AF33: 0 | AG33: =SUM(AB33:AF33) -> 0 | AH33: 0 | AI33: 0
A34: 5710 | B34: 1970 | C34: =2026-B34 -> 56 | D34: {=_xlfn.IFS(C34<36,"Young",C34<56,"Middle-aged",C34>=56,"Senior")} -> Senior | E34: Graduation | F34: Together | G34: 40548 | H34: =IF(G34=0,MEDIAN(Income),G34) -> 40548 | I34: {=_xlfn.IFS(H34<PERCENTILE(Income_Clean,0.33),"Low",H34<PERCENTILE(Income_Clean,0.67),"Medium",H34>PERCENTILE(Income_Clean,0.67),"High")} -> Medium | J34: =_xlfn.XLOOKUP(I34,$AK$3:$AK$5,$AL$3:$AL$5) -> Average Income | K34: 0 | L34: 1 | M34: =IF(K34+L34>0,"Yes","No") -> Yes | N34: 2012-10-10 | O34: 31 | P34: 110 | Q34: 0 | R34: 5 | S34: 2 | T34: 0 | U34: 3 | V34: =SUM(P34:U34) -> 120 | W34: 2 | X34: 2 | Y34: 1 | Z34: 4 | AA34: 5 | AB34: 0 | AC34: 1 | AD34: 0 | AE34: 0 | AF34: 0 | AG34: =SUM(AB34:AF34) -> 1 | AH34: 0 | AI34: 0
A35: 7373 | B35: 1952 | C35: =2026-B35 -> 74 | D35: {=_xlfn.IFS(C35<36,"Young",C35<56,"Middle-aged",C35>=56,"Senior")} -> Senior | E35: PhD | F35: Divorced | G35: 46610 | H35: =IF(G35=0,MEDIAN(Income),G35) -> 46610 | I35: {=_xlfn.IFS(H35<PERCENTILE(Income_Clean,0.33),"Low",H35<PERCENTILE(Income_Clean,0.67),"Medium",H35>PERCENTILE(Income_Clean,0.67),"High")} -> Medium | J35: =_xlfn.XLOOKUP(I35,$AK$3:$AK$5,$AL$3:$AL$5) -> Average Income | K35: 0 | L35: 2 | M35: =IF(K35+L35>0,"Yes","No") -> Yes | N35: 2012-10-29 | O35: 8 | P35: 96 | Q35: 12 | R35: 96 | S35: 33 | T35: 22 | U35: 43 | V35: =SUM(P35:U35) -> 302 | W35: 6 | X35: 4 | Y35: 1 | Z35: 6 | AA35: 6 | AB35: 0 | AC35: 0 | AD35: 0 | AE35: 0 | AF35: 0 | AG35: =SUM(AB35:AF35) -> 0 | AH35: 0 | AI35: 1
A36: 8755 | B36: 1946 | C36: =2026-B36 -> 80 | D36: {=_xlfn.IFS(C36<36,"Young",C36<56,"Middle-aged",C36>=56,"Senior")} -> Senior | E36: Master | F36: Married | G36: 68657 | H36: =IF(G36=0,MEDIAN(Income),G36) -> 68657 | I36: {=_xlfn.IFS(H36<PERCENTILE(Income_Clean,0.33),"Low",H36<PERCENTILE(Income_Clean,0.67),"Medium",H36>PERCENTILE(Income_Clean,0.67),"High")} -> High | J36: =_xlfn.XLOOKUP(I36,$AK$3:$AK$5,$AL$3:$AL$5) -> Above Average Income | K36: 0 | L36: 0 | M36: =IF(K36+L36>0,"Yes","No") -> No | N36: 2013-02-20 | O36: 4 | P36: 482 | Q36: 34 | R36: 471 | S36: 119 | T36: 68 | U36: 22 | V36: =SUM(P36:U36) -> 1196 | W36: 1 | X36: 3 | Y36: 5 | Z36: 9 | AA36: 7 | AB36: 0 | AC36: 0 | AD36: 0 | AE36: 0 | AF36: 0 | AG36: =SUM(AB36:AF36) -> 0 | AH36: 0 | AI36: 0
A37: 10738 | B37: 1951 | C37: =2026-B37 -> 75 | D37: {=_xlfn.IFS(C37<36,"Young",C37<56,"Middle-aged",C37>=56,"Senior")} -> Senior | E37: Master | F37: Single | G37: 49389 | H37: =IF(G37=0,MEDIAN(Income),G37) -> 49389 | I37: {=_xlfn.IFS(H37<PERCENTILE(Income_Clean,0.33),"Low",H37<PERCENTILE(Income_Clean,0.67),"Medium",H37>PERCENTILE(Income_Clean,0.67),"High")} -> Medium | J37: =_xlfn.XLOOKUP(I37,$AK$3:$AK$5,$AL$3:$AL$5) -> Average Income | K37: 1 | L37: 1 | M37: =IF(K37+L37>0,"Yes","No") -> Yes | N37: 2013-08-29 | O37: 55 | P37: 40 | Q37: 0 | R37: 19 | S37: 2 | T37: 1 | U37: 3 | V37: =SUM(P37:U37) -> 65 | W37: 1 | X37: 2 | Y37: 0 | Z37: 3 | AA37: 7 | AB37: 0 | AC37: 0 | AD37: 0 | AE37: 0 | AF37: 0 | AG37: =SUM(AB37:AF37) -> 0 | AH37: 0 | AI37: 0
A38: 4339 | B38: 1970 | C38: =2026-B38 -> 56 | D38: {=_xlfn.IFS(C38<36,"Young",C38<56,"Middle-aged",C38>=56,"Senior")} -> Senior | E38: PhD | F38: Married | G38: 67353 | H38: =IF(G38=0,MEDIAN(Income),G38) -> 67353 | I38: {=_xlfn.IFS(H38<PERCENTILE(Income_Clean,0.33),"Low",H38<PERCENTILE(Income_Clean,0.67),"Medium",H38>PERCENTILE(Income_Clean,0.67),"High")} -> High | J38: =_xlfn.XLOOKUP(I38,$AK$3:$AK$5,$AL$3:$AL$5) -> Above Average Income | K38: 0 | L38: 1 | M38: =IF(K38+L38>0,"Yes","No") -> Yes | N38: 2013-12-31 | O38: 37 | P38: 702 | Q38: 17 | R38: 151 | S38: 0 | T38: 8 | U38: 35 | V38: =SUM(P38:U38) -> 913 | W38: 5 | X38: 5 | Y38: 6 | Z38: 12 | AA38: 2 | AB38: 0 | AC38: 0 | AD38: 0 | AE38: 0 | AF38: 0 | AG38: =SUM(AB38:AF38) -> 0 | AH38: 0 | AI38: 0
A39: 10755 | B39: 1976 | C39: =2026-B39 -> 50 | D39: {=_xlfn.IFS(C39<36,"Young",C39<56,"Middle-aged",C39>=56,"Senior")} -> Middle-aged | E39: 2n Cycle | F39: Married | G39: 23718 | H39: =IF(G39=0,MEDIAN(Income),G39) -> 23718 | I39: {=_xlfn.IFS(H39<PERCENTILE(Income_Clean,0.33),"Low",H39<PERCENTILE(Income_Clean,0.67),"Medium",H39>PERCENTILE(Income_Clean,0.67),"High")} -> Low | J39: =_xlfn.XLOOKUP(I39,$AK$3:$AK$5,$AL$3:$AL$5) -> Below Average Income | K39: 1 | L39: 0 | M39: =IF(K39+L39>0,"Yes","No") -> Yes | N39: 2013-09-02 | O39: 76 | P39: 6 | Q39: 3 | R39: 14 | S39: 15 | T39: 7 | U39: 36 | V39: =SUM(P39:U39) -> 81 | W39: 3 | X39: 3 | Y39: 1 | Z39: 2 | AA39: 7 | AB39: 0 | AC39: 0 | AD39: 0 | AE39: 0 | AF39: 0 | AG39: =SUM(AB39:AF39) -> 0 | AH39: 0 | AI39: 0
A40: 8595 | B40: 1973 | C40: =2026-B40 -> 53 | D40: {=_xlfn.IFS(C40<36,"Young",C40<56,"Middle-aged",C40>=56,"Senior")} -> Middle-aged | E40: Graduation | F40: Widow | G40: 42429 | H40: =IF(G40=0,MEDIAN(Income),G40) -> 42429 | I40: {=_xlfn.IFS(H40<PERCENTILE(Income_Clean,0.33),"Low",H40<PERCENTILE(Income_Clean,0.67),"Medium",H40>PERCENTILE(Income_Clean,0.67),"High")} -> Medium | J40: =_xlfn.XLOOKUP(I40,$AK$3:$AK$5,$AL$3:$AL$5) -> Average Income | K40: 0 | L40: 1 | M40: =IF(K40+L40>0,"Yes","No") -> Yes | N40: 2014-02-11 | O40: 99 | P40: 55 | Q40: 0 | R40: 6 | S40: 2 | T40: 0 | U40: 4 | V40: =SUM(P40:U40) -> 67 | W40: 2 | X40: 1 | Y40: 1 | Z40: 3 | AA40: 5 | AB40: 0 | AC40: 0 | AD40: 0 | AE40: 0 | AF40: 0 | AG40: =SUM(AB40:AF40) -> 0 | AH40: 0 | AI40: 0
A41: 2968 | B41: 1943 | C41: =2026-B41 -> 83 | D41: {=_xlfn.IFS(C41<36,"Young",C41<56,"Middle-aged",C41>=56,"Senior")} -> Senior | E41: PhD | F41: Divorced | G41: 48948 | H41: =IF(G41=0,MEDIAN(Income),G41) -> 48948 | I41: {=_xlfn.IFS(H41<PERCENTILE(Income_Clean,0.33),"Low",H41<PERCENTILE(Income_Clean,0.67),"Medium",H41>PERCENTILE(Income_Clean,0.67),"High")} -> Medium | J41: =_xlfn.XLOOKUP(I41,$AK$3:$AK$5,$AL$3:$AL$5) -> Average Income | K41: 0 | L41: 0 | M41: =IF(K41+L41>0,"Yes","No") -> No | N41: 2013-02-01 | O41: 53 | P41: 437 | Q41: 8 | R41: 206 | S41: 160 | T41: 49 | U41: 42 | V41: =SUM(P41:U41) -> 902 | W41: 2 | X41: 7 | Y41: 10 | Z41: 5 | AA41: 6 | AB41: 1 | AC41: 0 | AD41: 0 | AE41: 0 | AF41: 0 | AG41: =SUM(AB41:AF41) -> 1 | AH41: 0 | AI41: 1
... A44: 8430 | B44: 1957 | C44: =2026-B44 -> 69 | D44: {=_xlfn.IFS(C44<36,"Young",C44<56,"Middle-aged",C44>=56,"Senior")} -> Senior | E44: Graduation | F44: Together | G44: 21994 | H44: =IF(G44=0,MEDIAN(Income),G44) -> 21994 | I44: {=_xlfn.IFS(H44<PERCENTILE(Income_Clean,0.33),"Low",H44<PERCENTILE(Income_Clean,0.67),"Medium",H44>PERCENTILE(Income_Clean,0.67),"High")} -> Low | J44: =_xlfn.XLOOKUP(I44,$AK$3:$AK$5,$AL$3:$AL$5) -> Below Average Income | K44: 0 | L44: 1 | M44: =IF(K44+L44>0,"Yes","No") -> Yes | N44: 2012-12-24 | O44: 4 | P44: 9 | Q44: 0 | R44: 6 | S44: 3 | T44: 1 | U44: 3 | V44: =SUM(P44:U44) -> 22 | W44: 1 | X44: 0 | Y44: 0 | Z44: 3 | AA44: 5 | AB44: 0 | AC44: 0 | AD44: 0 | AE44: 0 | AF44: 0 | AG44: =SUM(AB44:AF44) -> 0 | AH44: 0 | AI44: 0
A45: 7281 | B45: 1959 | C45: =2026-B45 -> 67 | D45: {=_xlfn.IFS(C45<36,"Young",C45<56,"Middle-aged",C45>=56,"Senior")} -> Senior | E45: PhD | F45: Single | H45: =IF(G45=0,MEDIAN(Income),G45) -> 51371 | I45: {=_xlfn.IFS(H45<PERCENTILE(Income_Clean,0.33),"Low",H45<PERCENTILE(Income_Clean,0.67),"Medium",H45>PERCENTILE(Income_Clean,0.67),"High")} -> Medium | J45: =_xlfn.XLOOKUP(I45,$AK$3:$AK$5,$AL$3:$AL$5) -> Average Income | K45: 0 | L45: 0 | M45: =IF(K45+L45>0,"Yes","No") -> No | N45: 2013-11-05 | O45: 80 | P45: 81 | Q45: 11 | R45: 50 | S45: 3 | T45: 2 | U45: 39 | V45: =SUM(P45:U45) -> 186 | W45: 1 | X45: 1 | Y45: 3 | Z45: 4 | AA45: 2 | AB45: 0 | AC45: 0 | AD45: 0 | AE45: 0 | AF45: 0 | AG45: =SUM(AB45:AF45) -> 0 | AH45: 0 | AI45: 0
A46: 2139 | B46: 1975 | C46: =2026-B46 -> 51 | D46: {=_xlfn.IFS(C46<36,"Young",C46<56,"Middle-aged",C46>=56,"Senior")} -> Middle-aged | E46: Master | F46: Married | G46: 7500 | H46: =IF(G46=0,MEDIAN(Income),G46) -> 7500 | I46: {=_xlfn.IFS(H46<PERCENTILE(Income_Clean,0.33),"Low",H46<PERCENTILE(Income_Clean,0.67),"Medium",H46>PERCENTILE(Income_Clean,0.67),"High")} -> Low | J46: =_xlfn.XLOOKUP(I46,$AK$3:$AK$5,$AL$3:$AL$5) -> Below Average Income | K46: 1 | L46: 0 | M46: =IF(K46+L46>0,"Yes","No") -> Yes | N46: 2013-10-02 | O46: 19 | P46: 3 | Q46: 1 | R46: 10 | S46: 3 | T46: 2 | U46: 12 | V46: =SUM(P46:U46) -> 31 | W46: 3 | X46: 2 | Y46: 0 | Z46: 3 | AA46: 5 | AB46: 0 | AC46: 0 | AD46: 0 | AE46: 0 | AF46: 0 | AG46: =SUM(AB46:AF46) -> 0 | AH46: 0 | AI46: 0
A47: 1371 | B47: 1976 | C47: =2026-B47 -> 50 | D47: {=_xlfn.IFS(C47<36,"Young",C47<56,"Middle-aged",C47>=56,"Senior")} -> Middle-aged | E47: Graduation | F47: Single | G47: 79941 | H47: =IF(G47=0,MEDIAN(Income),G47) -> 79941 | I47: {=_xlfn.IFS(H47<PERCENTILE(Income_Clean,0.33),"Low",H47<PERCENTILE(Income_Clean,0.67),"Medium",H47>PERCENTILE(Income_Clean,0.67),"High")} -> High | J47: =_xlfn.XLOOKUP(I47,$AK$3:$AK$5,$AL$3:$AL$5) -> Above Average Income | K47: 0 | L47: 0 | M47: =IF(K47+L47>0,"Yes","No") -> No | N47: 2014-06-28 | O47: 72 | P47: 123 | Q47: 164 | R47: 266 | S47: 227 | T47: 30 | U47: 174 | V47: =SUM(P47:U47) -> 984 | W47: 1 | X47: 2 | Y47: 4 | Z47: 9 | AA47: 1 | AB47: 0 | AC47: 0 | AD47: 0 | AE47: 0 | AF47: 0 | AG47: =SUM(AB47:AF47) -> 0 | AH47: 0 | AI47: 0
A48: 9909 | B48: 1996 | C48: =2026-B48 -> 30 | D48: {=_xlfn.IFS(C48<36,"Young",C48<56,"Middle-aged",C48>=56,"Senior")} -> Young | E48: 2n Cycle | F48: Married | G48: 7500 | H48: =IF(G48=0,MEDIAN(Income),G48) -> 7500 | I48: {=_xlfn.IFS(H48<PERCENTILE(Income_Clean,0.33),"Low",H48<PERCENTILE(Income_Clean,0.67),"Medium",H48>PERCENTILE(Income_Clean,0.67),"High")} -> Low | J48: =_xlfn.XLOOKUP(I48,$AK$3:$AK$5,$AL$3:$AL$5) -> Below Average Income | K48: 0 | L48: 0 | M48: =IF(K48+L48>0,"Yes","No") -> No | N48: 2012-11-09 | O48: 24 | P48: 3 | Q48: 18 | R48: 14 | S48: 15 | T48: 22 | U48: 50 | V48: =SUM(P48:U48) -> 122 | W48: 3 | X48: 3 | Y48: 1 | Z48: 3 | AA48: 9 | AB48: 0 | AC48: 0 | AD48: 0 | AE48: 0 | AF48: 0 | AG48: =SUM(AB48:AF48) -> 0 | AH48: 0 | AI48: 1
A49: 7286 | B49: 1968 | C49: =2026-B49 -> 58 | D49: {=_xlfn.IFS(C49<36,"Young",C49<56,"Middle-aged",C49>=56,"Senior")} -> Senior | E49: Graduation | F49: Together | G49: 41728 | H49: =IF(G49=0,MEDIAN(Income),G49) -> 41728 | I49: {=_xlfn.IFS(H49<PERCENTILE(Income_Clean,0.33),"Low",H49<PERCENTILE(Income_Clean,0.67),"Medium",H49>PERCENTILE(Income_Clean,0.67),"High")} -> Medium | J49: =_xlfn.XLOOKUP(I49,$AK$3:$AK$5,$AL$3:$AL$5) -> Average Income | K49: 1 | L49: 0 | M49: =IF(K49+L49>0,"Yes","No") -> Yes | N49: 2013-05-24 | O49: 92 | P49: 13 | Q49: 6 | R49: 15 | S49: 3 | T49: 5 | U49: 13 | V49: =SUM(P49:U49) -> 55 | W49: 1 | X49: 2 | Y49: 0 | Z49: 2 | AA49: 10 | AB49: 0 | AC49: 0 | AD49: 0 | AE49: 0 | AF49: 0 | AG49: =SUM(AB49:AF49) -> 0 | AH49: 0 | AI49: 0
A50: 7244 | B50: 1951 | C50: =2026-B50 -> 75 | D50: {=_xlfn.IFS(C50<36,"Young",C50<56,"Middle-aged",C50>=56,"Senior")} -> Senior | E50: Graduation | F50: Single | H50: =IF(G50=0,MEDIAN(Income),G50) -> 51371 | I50: {=_xlfn.IFS(H50<PERCENTILE(Income_Clean,0.33),"Low",H50<PERCENTILE(Income_Clean,0.67),"Medium",H50>PERCENTILE(Income_Clean,0.67),"High")} -> Medium | J50: =_xlfn.XLOOKUP(I50,$AK$3:$AK$5,$AL$3:$AL$5) -> Average Income | K50: 2 | L50: 1 | M50: =IF(K50+L50>0,"Yes","No") -> Yes | N50: 2014-01-01 | O50: 96 | P50: 48 | Q50: 5 | R50: 48 | S50: 6 | T50: 10 | U50: 7 | V50: =SUM(P50:U50) -> 124 | W50: 3 | X50: 2 | Y50: 1 | Z50: 4 | AA50: 6 | AB50: 0 | AC50: 0 | AD50: 0 | AE50: 0 | AF50: 0 | AG50: =SUM(AB50:AF50) -> 0 | AH50: 0 | AI50: 0
A51: 6566 | B51: 1954 | C51: =2026-B51 -> 72 | D51: {=_xlfn.IFS(C51<36,"Young",C51<56,"Middle-aged",C51>=56,"Senior")} -> Senior | E51: PhD | F51: Married | G51: 72550 | H51: =IF(G51=0,MEDIAN(Income),G51) -> 72550 | I51: {=_xlfn.IFS(H51<PERCENTILE(Income_Clean,0.33),"Low",H51<PERCENTILE(Income_Clean,0.67),"Medium",H51>PERCENTILE(Income_Clean,0.67),"High")} -> High | J51: =_xlfn.XLOOKUP(I51,$AK$3:$AK$5,$AL$3:$AL$5) -> Above Average Income | K51: 1 | L51: 1 | M51: =IF(K51+L51>0,"Yes","No") -> Yes | N51: 2012-11-08 | O51: 39 | P51: 826 | Q51: 50 | R51: 317 | S51: 50 | T51: 38 | U51: 38 | V51: =SUM(P51:U51) -> 1319 | W51: 9 | X51: 5 | Y51: 2 | Z51: 12 | AA51: 8 | AB51: 0 | AC51: 0 | AD51: 0 | AE51: 0 | AF51: 0 | AG51: =SUM(AB51:AF51) -> 0 | AH51: 0 | AI51: 0
A52: 8614 | B52: 1957 | C52: =2026-B52 -> 69 | D52: {=_xlfn.IFS(C52<36,"Young",C52<56,"Middle-aged",C52>=56,"Senior")} -> Senior | E52: Graduation | F52: Widow | G52: 65486 | H52: =IF(G52=0,MEDIAN(Income),G52) -> 65486 | I52: {=_xlfn.IFS(H52<PERCENTILE(Income_Clean,0.33),"Low",H52<PERCENTILE(Income_Clean,0.67),"Medium",H52>PERCENTILE(Income_Clean,0.67),"High")} -> High | J52: =_xlfn.XLOOKUP(I52,$AK$3:$AK$5,$AL$3:$AL$5) -> Above Average Income | K52: 0 | L52: 1 | M52: =IF(K52+L52>0,"Yes","No") -> Yes | N52: 2014-05-12 | O52: 29 | P52: 245 | Q52: 19 | R52: 125 | S52: 37 | T52: 67 | U52: 14 | V52: =SUM(P52:U52) -> 507 | W52: 1 | X52: 4 | Y52: 2 | Z52: 10 | AA52: 2 | AB52: 0 | AC52: 0 | AD52: 0 | AE52: 0 | AF52: 0 | AG52: =SUM(AB52:AF52) -> 0 | AH52: 0 | AI52: 0
A53: 4114 | B53: 1964 | C53: =2026-B53 -> 62 | D53: {=_xlfn.IFS(C53<36,"Young",C53<56,"Middle-aged",C53>=56,"Senior")} -> Senior | E53: Master | F53: Married | G53: 79143 | H53: =IF(G53=0,MEDIAN(Income),G53) -> 79143 | I53: {=_xlfn.IFS(H53<PERCENTILE(Income_Clean,0.33),"Low",H53<PERCENTILE(Income_Clean,0.67),"Medium",H53>PERCENTILE(Income_Clean,0.67),"High")} -> High | J53: =_xlfn.XLOOKUP(I53,$AK$3:$AK$5,$AL$3:$AL$5) -> Above Average Income | K53: 0 | L53: 0 | M53: =IF(K53+L53>0,"Yes","No") -> No | N53: 2012-08-11 | O53: 2 | P53: 650 | Q53: 37 | R53: 780 | S53: 27 | T53: 167 | U53: 32 | V53: =SUM(P53:U53) -> 1693 | W53: 1 | X53: 6 | Y53: 9 | Z53: 13 | AA53: 3 | AB53: 0 | AC53: 0 | AD53: 0 | AE53: 0 | AF53: 0 | AG53: =SUM(AB53:AF53) -> 0 | AH53: 0 | AI53: 0
A54: 1331 | B54: 1977 | C54: =2026-B54 -> 49 | D54: {=_xlfn.IFS(C54<36,"Young",C54<56,"Middle-aged",C54>=56,"Senior")} -> Middle-aged | E54: Graduation | F54: Single | G54: 35790 | H54: =IF(G54=0,MEDIAN(Income),G54) -> 35790 | I54: {=_xlfn.IFS(H54<PERCENTILE(Income_Clean,0.33),"Low",H54<PERCENTILE(Income_Clean,0.67),"Medium",H54>PERCENTILE(Income_Clean,0.67),"High")} -> Low | J54: =_xlfn.XLOOKUP(I54,$AK$3:$AK$5,$AL$3:$AL$5) -> Below Average Income | K54: 1 | L54: 0 | M54: =IF(K54+L54>0,"Yes","No") -> Yes | N54: 2013-01-02 | O54: 54 | P54: 12 | Q54: 6 | R54: 20 | S54: 30 | T54: 1 | U54: 3 | V54: =SUM(P54:U54) -> 72 | W54: 2 | X54: 2 | Y54: 0 | Z54: 3 | AA54: 7 | AB54: 0 | AC54: 0 | AD54: 0 | AE54: 0 | AF54: 0 | AG54: =SUM(AB54:AF54) -> 0 | AH54: 0 | AI54: 0
A55: 2225 | B55: 1977 | C55: =2026-B55 -> 49 | D55: {=_xlfn.IFS(C55<36,"Young",C55<56,"Middle-aged",C55>=56,"Senior")} -> Middle-aged | E55: Graduation | F55: Divorced | G55: 82582 | H55: =IF(G55=0,MEDIAN(Income),G55) -> 82582 | I55: {=_xlfn.IFS(H55<PERCENTILE(Income_Clean,0.33),"Low",H55<PERCENTILE(Income_Clean,0.67),"Medium",H55>PERCENTILE(Income_Clean,0.67),"High")} -> High | J55: =_xlfn.XLOOKUP(I55,$AK$3:$AK$5,$AL$3:$AL$5) -> Above Average Income | K55: 0 | L55: 0 | M55: =IF(K55+L55>0,"Yes","No") -> No | N55: 2014-06-07 | O55: 54 | P55: 510 | Q55: 120 | R55: 550 | S55: 156 | T55: 40 | U55: 241 | V55: =SUM(P55:U55) -> 1617 | W55: 1 | X55: 4 | Y55: 9 | Z55: 7 | AA55: 1 | AB55: 1 | AC55: 0 | AD55: 0 | AE55: 1 | AF55: 0 | AG55: =SUM(AB55:AF55) -> 2 | AH55: 0 | AI55: 1
A56: 9381 | B56: 1978 | C56: =2026-B56 -> 48 | D56: {=_xlfn.IFS(C56<36,"Young",C56<56,"Middle-aged",C56>=56,"Senior")} -> Middle-aged | E56: Graduation | F56: Married | G56: 66373 | H56: =IF(G56=0,MEDIAN(Income),G56) -> 66373 | I56: {=_xlfn.IFS(H56<PERCENTILE(Income_Clean,0.33),"Low",H56<PERCENTILE(Income_Clean,0.67),"Medium",H56>PERCENTILE(Income_Clean,0.67),"High")} -> High | J56: =_xlfn.XLOOKUP(I56,$AK$3:$AK$5,$AL$3:$AL$5) -> Above Average Income | K56: 1 | L56: 1 | M56: =IF(K56+L56>0,"Yes","No") -> Yes | N56: 2013-06-12 | O56: 57 | P56: 328 | Q56: 9 | R56: 124 | S56: 12 | T56: 24 | U56: 109 | V56: =SUM(P56:U56) -> 606 | W56: 7 | X56: 4 | Y56: 2 | Z56: 10 | AA56: 3 | AB56: 0 | AC56: 0 | AD56: 0 | AE56: 0 | AF56: 0 | AG56: =SUM(AB56:AF56) -> 0 | AH56: 0 | AI56: 0
A57: 6260 | B57: 1955 | C57: =2026-B57 -> 71 | D57: {=_xlfn.IFS(C57<36,"Young",C57<56,"Middle-aged",C57>=56,"Senior")} -> Senior | E57: Master | F57: Together | G57: 82384 | H57: =IF(G57=0,MEDIAN(Income),G57) -> 82384 | I57: {=_xlfn.IFS(H57<PERCENTILE(Income_Clean,0.33),"Low",H57<PERCENTILE(Income_Clean,0.67),"Medium",H57>PERCENTILE(Income_Clean,0.67),"High")} -> High | J57: =_xlfn.XLOOKUP(I57,$AK$3:$AK$5,$AL$3:$AL$5) -> Above Average Income | K57: 0 | L57: 0 | M57: =IF(K57+L57>0,"Yes","No") -> No | N57: 2012-11-19 | O57: 55 | P57: 984 | Q57: 51 | R57: 432 | S57: 180 | T57: 120 | U57: 190 | V57: =SUM(P57:U57) -> 1957 | W57: 1 | X57: 3 | Y57: 10 | Z57: 13 | AA57: 1 | AB57: 0 | AC57: 0 | AD57: 1 | AE57: 0 | AF57: 0 | AG57: =SUM(AB57:AF57) -> 1 | AH57: 0 | AI57: 1
A58: 10383 | B58: 1966 | C58: =2026-B58 -> 60 | D58: {=_xlfn.IFS(C58<36,"Young",C58<56,"Middle-aged",C58>=56,"Senior")} -> Senior | E58: Graduation | F58: Divorced | G58: 70287 | H58: =IF(G58=0,MEDIAN(Income),G58) -> 70287 | I58: {=_xlfn.IFS(H58<PERCENTILE(Income_Clean,0.33),"Low",H58<PERCENTILE(Income_Clean,0.67),"Medium",H58>PERCENTILE(Income_Clean,0.67),"High")} -> High | J58: =_xlfn.XLOOKUP(I58,$AK$3:$AK$5,$AL$3:$AL$5) -> Above Average Income | K58: 0 | L58: 0 | M58: =IF(K58+L58>0,"Yes","No") -> No | N58: 2013-04-02 | O58: 30 | P58: 295 | Q58: 35 | R58: 482 | S58: 121 | T58: 120 | U58: 40 | V58: =SUM(P58:U58) -> 1093 | W58: 1 | X58: 5 | Y58: 5 | Z58: 10 | AA58: 3 | AB58: 0 | AC58: 0 | AD58: 0 | AE58: 0 | AF58: 0 | AG58: =SUM(AB58:AF58) -> 0 | AH58: 0 | AI58: 1
A59: 7437 | B59: 1988 | C59: =2026-B59 -> 38 | D59: {=_xlfn.IFS(C59<36,"Young",C59<56,"Middle-aged",C59>=56,"Senior")} -> Middle-aged | E59: Graduation | F59: Single | G59: 27938 | H59: =IF(G59=0,MEDIAN(Income),G59) -> 27938 | I59: {=_xlfn.IFS(H59<PERCENTILE(Income_Clean,0.33),"Low",H59<PERCENTILE(Income_Clean,0.67),"Medium",H59>PERCENTILE(Income_Clean,0.67),"High")} -> Low | J59: =_xlfn.XLOOKUP(I59,$AK$3:$AK$5,$AL$3:$AL$5) -> Below Average Income | K59: 1 | L59: 0 | M59: =IF(K59+L59>0,"Yes","No") -> Yes | N59: 2014-04-28 | O59: 31 | P59: 13 | Q59: 0 | R59: 8 | S59: 2 | T59: 1 | U59: 5 | V59: =SUM(P59:U59) -> 29 | W59: 1 | X59: 1 | Y59: 0 | Z59: 4 | AA59: 3 | AB59: 0 | AC59: 0 | AD59: 0 | AE59: 0 | AF59: 0 | AG59: =SUM(AB59:AF59) -> 0 | AH59: 0 | AI59: 0
A60: 8557 | B60: 1982 | C60: =2026-B60 -> 44 | D60: {=_xlfn.IFS(C60<36,"Young",C60<56,"Middle-aged",C60>=56,"Senior")} -> Middle-aged | E60: Graduation | F60: Single | H60: =IF(G60=0,MEDIAN(Income),G60) -> 51371 | I60: {=_xlfn.IFS(H60<PERCENTILE(Income_Clean,0.33),"Low",H60<PERCENTILE(Income_Clean,0.67),"Medium",H60>PERCENTILE(Income_Clean,0.67),"High")} -> Medium | J60: =_xlfn.XLOOKUP(I60,$AK$3:$AK$5,$AL$3:$AL$5) -> Average Income | K60: 1 | L60: 0 | M60: =IF(K60+L60>0,"Yes","No") -> Yes | N60: 2013-06-17 | O60: 57 | P60: 11 | Q60: 3 | R60: 22 | S60: 2 | T60: 2 | U60: 6 | V60: =SUM(P60:U60) -> 46 | W60: 2 | X60: 2 | Y60: 0 | Z60: 3 | AA60: 6 | AB60: 0 | AC60: 0 | AD60: 0 | AE60: 0 | AF60: 0 | AG60: =SUM(AB60:AF60) -> 0 | AH60: 0 | AI60: 0
A61: 8375 | B61: 1968 | C61: =2026-B61 -> 58 | D61: {=_xlfn.IFS(C61<36,"Young",C61<56,"Middle-aged",C61>=56,"Senior")} -> Senior | E61: PhD | F61: Married | G61: 55954 | H61: =IF(G61=0,MEDIAN(Income),G61) -> 55954 | I61: {=_xlfn.IFS(H61<PERCENTILE(Income_Clean,0.33),"Low",H61<PERCENTILE(Income_Clean,0.67),"Medium",H61>PERCENTILE(Income_Clean,0.67),"High")} -> Medium | J61: =_xlfn.XLOOKUP(I61,$AK$3:$AK$5,$AL$3:$AL$5) -> Average Income | K61: 0 | L61: 1 | M61: =IF(K61+L61>0,"Yes","No") -> Yes | N61: 2014-03-03 | O61: 63 | P61: 447 | Q61: 0 | R61: 28 | S61: 0 | T61: 0 | U61: 43 | V61: =SUM(P61:U61) -> 518 | W61: 3 | X61: 8 | Y61: 2 | Z61: 6 | AA61: 7 | AB61: 0 | AC61: 0 | AD61: 0 | AE61: 0 | AF61: 0 | AG61: =SUM(AB61:AF61) -> 0 | AH61: 0 | AI61: 0
A62: 6853 | B62: 1982 | C62: =2026-B62 -> 44 | D62: {=_xlfn.IFS(C62<36,"Young",C62<56,"Middle-aged",C62>=56,"Senior")} -> Middle-aged | E62: Master | F62: Single | G62: 75777 | H62: =IF(G62=0,MEDIAN(Income),G62) -> 75777 | I62: {=_xlfn.IFS(H62<PERCENTILE(Income_Clean,0.33),"Low",H62<PERCENTILE(Income_Clean,0.67),"Medium",H62>PERCENTILE(Income_Clean,0.67),"High")} -> High | J62: =_xlfn.XLOOKUP(I62,$AK$3:$AK$5,$AL$3:$AL$5) -> Above Average Income | K62: 0 | L62: 0 | M62: =IF(K62+L62>0,"Yes","No") -> No | N62: 2013-07-04 | O62: 12 | P62: 712 | Q62: 26 | R62: 538 | S62: 69 | T62: 13 | U62: 80 | V62: =SUM(P62:U62) -> 1438 | W62: 1 | X62: 3 | Y62: 6 | Z62: 11 | AA62: 1 | AB62: 0 | AC62: 1 | AD62: 1 | AE62: 0 | AF62: 0 | AG62: =SUM(AB62:AF62) -> 2 | AH62: 0 | AI62: 1
A63: 3076 | B63: 1975 | C63: =2026-B63 -> 51 | D63: {=_xlfn.IFS(C63<36,"Young",C63<56,"Middle-aged",C63>=56,"Senior")} -> Middle-aged | E63: Graduation | F63: Together | G63: 66653 | H63: =IF(G63=0,MEDIAN(Income),G63) -> 66653 | I63: {=_xlfn.IFS(H63<PERCENTILE(Income_Clean,0.33),"Low",H63<PERCENTILE(Income_Clean,0.67),"Medium",H63>PERCENTILE(Income_Clean,0.67),"High")} -> High | J63: =_xlfn.XLOOKUP(I63,$AK$3:$AK$5,$AL$3:$AL$5) -> Above Average Income | K63: 1 | L63: 1 | M63: =IF(K63+L63>0,"Yes","No") -> Yes | N63: 2012-09-07 | O63: 18 | P63: 452 | Q63: 18 | R63: 102 | S63: 16 | T63: 18 | U63: 6 | V63: =SUM(P63:U63) -> 612 | W63: 4 | X63: 4 | Y63: 2 | Z63: 12 | AA63: 3 | AB63: 0 | AC63: 0 | AD63: 0 | AE63: 0 | AF63: 0 | AG63: =SUM(AB63:AF63) -> 0 | AH63: 0 | AI63: 0
A64: 1012 | B64: 1952 | C64: =2026-B64 -> 74 | D64: {=_xlfn.IFS(C64<36,"Young",C64<56,"Middle-aged",C64>=56,"Senior")} -> Senior | E64: Graduation | F64: Single | G64: 61823 | H64: =IF(G64=0,MEDIAN(Income),G64) -> 61823 | I64: {=_xlfn.IFS(H64<PERCENTILE(Income_Clean,0.33),"Low",H64<PERCENTILE(Income_Clean,0.67),"Medium",H64>PERCENTILE(Income_Clean,0.67),"High")} -> Medium | J64: =_xlfn.XLOOKUP(I64,$AK$3:$AK$5,$AL$3:$AL$5) -> Average Income | K64: 0 | L64: 1 | M64: =IF(K64+L64>0,"Yes","No") -> Yes | N64: 2013-02-18 | O64: 26 | P64: 523 | Q64: 7 | R64: 134 | S64: 37 | T64: 14 | U64: 169 | V64: =SUM(P64:U64) -> 884 | W64: 4 | X64: 8 | Y64: 2 | Z64: 10 | AA64: 7 | AB64: 0 | AC64: 0 | AD64: 0 | AE64: 0 | AF64: 0 | AG64: =SUM(AB64:AF64) -> 0 | AH64: 0 | AI64: 0
A65: 6518 | B65: 1951 | C65: =2026-B65 -> 75 | D65: {=_xlfn.IFS(C65<36,"Young",C65<56,"Middle-aged",C65>=56,"Senior")} -> Senior | E65: PhD | F65: Widow | G65: 67680 | H65: =IF(G65=0,MEDIAN(Income),G65) -> 67680 | I65: {=_xlfn.IFS(H65<PERCENTILE(Income_Clean,0.33),"Low",H65<PERCENTILE(Income_Clean,0.67),"Medium",H65>PERCENTILE(Income_Clean,0.67),"High")} -> High | J65: =_xlfn.XLOOKUP(I65,$AK$3:$AK$5,$AL$3:$AL$5) -> Above Average Income | K65: 0 | L65: 1 | M65: =IF(K65+L65>0,"Yes","No") -> Yes | N65: 2013-06-11 | O65: 8 | P65: 546 | Q65: 0 | R65: 48 | S65: 0 | T65: 6 | U65: 6 | V65: =SUM(P65:U65) -> 606 | W65: 1 | X65: 7 | Y65: 3 | Z65: 8 | AA65: 5 | AB65: 0 | AC65: 0 | AD65: 0 | AE65: 0 | AF65: 0 | AG65: =SUM(AB65:AF65) -> 0 | AH65: 0 | AI65: 0
A66: 4137 | B66: 1948 | C66: =2026-B66 -> 78 | D66: {=_xlfn.IFS(C66<36,"Young",C66<56,"Middle-aged",C66>=56,"Senior")} -> Senior | E66: Graduation | F66: Together | G66: 70666 | H66: =IF(G66=0,MEDIAN(Income),G66) -> 70666 | I66: {=_xlfn.IFS(H66<PERCENTILE(Income_Clean,0.33),"Low",H66<PERCENTILE(Income_Clean,0.67),"Medium",H66>PERCENTILE(Income_Clean,0.67),"High")} -> High | J66: =_xlfn.XLOOKUP(I66,$AK$3:$AK$5,$AL$3:$AL$5) -> Above Average Income | K66: 0 | L66: 0 | M66: =IF(K66+L66>0,"Yes","No") -> No | N66: 2013-12-06 | O66: 29 | P66: 398 | Q66: 40 | R66: 367 | S66: 119 | T66: 122 | U66: 30 | V66: =SUM(P66:U66) -> 1076 | W66: 1 | X66: 7 | Y66: 4 | Z66: 4 | AA66: 4 | AB66: 0 | AC66: 0 | AD66: 0 | AE66: 0 | AF66: 0 | AG66: =SUM(AB66:AF66) -> 0 | AH66: 0 | AI66: 0
A67: 8082 | B67: 1971 | C67: =2026-B67 -> 55 | D67: {=_xlfn.IFS(C67<36,"Young",C67<56,"Middle-aged",C67>=56,"Senior")} -> Middle-aged | E67: Graduation | F67: Married | G67: 25721 | H67: =IF(G67=0,MEDIAN(Income),G67) -> 25721 | I67: {=_xlfn.IFS(H67<PERCENTILE(Income_Clean,0.33),"Low",H67<PERCENTILE(Income_Clean,0.67),"Medium",H67>PERCENTILE(Income_Clean,0.67),"High")} -> Low | J67: =_xlfn.XLOOKUP(I67,$AK$3:$AK$5,$AL$3:$AL$5) -> Below Average Income | K67: 1 | L67: 0 | M67: =IF(K67+L67>0,"Yes","No") -> Yes | N67: 2013-05-21 | O67: 75 | P67: 1 | Q67: 3 | R67: 6 | S67: 3 | T67: 6 | U67: 15 | V67: =SUM(P67:U67) -> 34 | W67: 1 | X67: 1 | Y67: 1 | Z67: 2 | AA67: 7 | AB67: 0 | AC67: 0 | AD67: 0 | AE67: 0 | AF67: 0 | AG67: =SUM(AB67:AF67) -> 0 | AH67: 0 | AI67: 1
A68: 1386 | B68: 1967 | C68: =2026-B68 -> 59 | D68: {=_xlfn.IFS(C68<36,"Young",C68<56,"Middle-aged",C68>=56,"Senior")} -> Senior | E68: Graduation | F68: Together | G68: 32474 | H68: =IF(G68=0,MEDIAN(Income),G68) -> 32474 | I68: {=_xlfn.IFS(H68<PERCENTILE(Income_Clean,0.33),"Low",H68<PERCENTILE(Income_Clean,0.67),"Medium",H68>PERCENTILE(Income_Clean,0.67),"High")} -> Low | J68: =_xlfn.XLOOKUP(I68,$AK$3:$AK$5,$AL$3:$AL$5) -> Below Average Income | K68: 1 | L68: 1 | M68: =IF(K68+L68>0,"Yes","No") -> Yes | N68: 2014-05-11 | O68: 0 | P68: 10 | Q68: 0 | R68: 1 | S68: 0 | T68: 0 | U68: 0 | V68: =SUM(P68:U68) -> 11 | W68: 1 | X68: 1 | Y68: 0 | Z68: 2 | AA68: 7 | AB68: 0 | AC68: 0 | AD68: 0 | AE68: 0 | AF68: 0 | AG68: =SUM(AB68:AF68) -> 0 | AH68: 0 | AI68: 0
A69: 9369 | B69: 1979 | C69: =2026-B69 -> 47 | D69: {=_xlfn.IFS(C69<36,"Young",C69<56,"Middle-aged",C69>=56,"Senior")} -> Middle-aged | E69: 2n Cycle | F69: Single | G69: 88194 | H69: =IF(G69=0,MEDIAN(Income),G69) -> 88194 | I69: {=_xlfn.IFS(H69<PERCENTILE(Income_Clean,0.33),"Low",H69<PERCENTILE(Income_Clean,0.67),"Medium",H69>PERCENTILE(Income_Clean,0.67),"High")} -> High | J69: =_xlfn.XLOOKUP(I69,$AK$3:$AK$5,$AL$3:$AL$5) -> Above Average Income | K69: 0 | L69: 1 | M69: =IF(K69+L69>0,"Yes","No") -> Yes | N69: 2014-03-19 | O69: 19 | P69: 688 | Q69: 14 | R69: 309 | S69: 201 | T69: 24 | U69: 38 | V69: =SUM(P69:U69) -> 1274 | W69: 1 | X69: 11 | Y69: 10 | Z69: 10 | AA69: 5 | AB69: 1 | AC69: 0 | AD69: 0 | AE69: 1 | AF69: 0 | AG69: =SUM(AB69:AF69) -> 2 | AH69: 0 | AI69: 1
A70: 4477 | B70: 1958 | C70: =2026-B70 -> 68 | D70: {=_xlfn.IFS(C70<36,"Young",C70<56,"Middle-aged",C70>=56,"Senior")} -> Senior | E70: Graduation | F70: Together | G70: 69096 | H70: =IF(G70=0,MEDIAN(Income),G70) -> 69096 | I70: {=_xlfn.IFS(H70<PERCENTILE(Income_Clean,0.33),"Low",H70<PERCENTILE(Income_Clean,0.67),"Medium",H70>PERCENTILE(Income_Clean,0.67),"High")} -> High | J70: =_xlfn.XLOOKUP(I70,$AK$3:$AK$5,$AL$3:$AL$5) -> Above Average Income | K70: 0 | L70: 1 | M70: =IF(K70+L70>0,"Yes","No") -> Yes | N70: 2013-09-27 | O70: 4 | P70: 247 | Q70: 49 | R70: 159 | S70: 7 | T70: 82 | U70: 109 | V70: =SUM(P70:U70) -> 653 | W70: 1 | X70: 5 | Y70: 2 | Z70: 10 | AA70: 4 | AB70: 0 | AC70: 0 | AD70: 0 | AE70: 0 | AF70: 0 | AG70: =SUM(AB70:AF70) -> 0 | AH70: 0 | AI70: 0
A71: 1357 | B71: 1970 | C71: =2026-B71 -> 56 | D71: {=_xlfn.IFS(C71<36,"Young",C71<56,"Middle-aged",C71>=56,"Senior")} -> Senior | E71: Graduation | F71: Together | G71: 74854 | H71: =IF(G71=0,MEDIAN(Income),G71) -> 74854 | I71: {=_xlfn.IFS(H71<PERCENTILE(Income_Clean,0.33),"Low",H71<PERCENTILE(Income_Clean,0.67),"Medium",H71>PERCENTILE(Income_Clean,0.67),"High")} -> High | J71: =_xlfn.XLOOKUP(I71,$AK$3:$AK$5,$AL$3:$AL$5) -> Above Average Income | K71: 1 | L71: 2 | M71: =IF(K71+L71>0,"Yes","No") -> Yes | N71: 2013-04-08 | O71: 90 | P71: 856 | Q71: 59 | R71: 487 | S71: 58 | T71: 29 | U71: 73 | V71: =SUM(P71:U71) -> 1562 | W71: 7 | X71: 2 | Y71: 5 | Z71: 5 | AA71: 5 | AB71: 0 | AC71: 0 | AD71: 0 | AE71: 0 | AF71: 0 | AG71: =SUM(AB71:AF71) -> 0 | AH71: 0 | AI71: 0
A72: 1402 | B72: 1954 | C72: =2026-B72 -> 72 | D72: {=_xlfn.IFS(C72<36,"Young",C72<56,"Middle-aged",C72>=56,"Senior")} -> Senior | E72: Master | F72: Married | G72: 66991 | H72: =IF(G72=0,MEDIAN(Income),G72) -> 66991 | I72: {=_xlfn.IFS(H72<PERCENTILE(Income_Clean,0.33),"Low",H72<PERCENTILE(Income_Clean,0.67),"Medium",H72>PERCENTILE(Income_Clean,0.67),"High")} -> High | J72: =_xlfn.XLOOKUP(I72,$AK$3:$AK$5,$AL$3:$AL$5) -> Above Average Income | K72: 0 | L72: 0 | M72: =IF(K72+L72>0,"Yes","No") -> No | N72: 2012-09-11 | O72: 1 | P72: 496 | Q72: 36 | R72: 460 | S72: 189 | T72: 60 | U72: 12 | V72: =SUM(P72:U72) -> 1253 | W72: 3 | X72: 4 | Y72: 8 | Z72: 6 | AA72: 3 | AB72: 0 | AC72: 0 | AD72: 0 | AE72: 0 | AF72: 0 | AG72: =SUM(AB72:AF72) -> 0 | AH72: 0 | AI72: 0
A73: 10629 | B73: 1973 | C73: =2026-B73 -> 53 | D73: {=_xlfn.IFS(C73<36,"Young",C73<56,"Middle-aged",C73>=56,"Senior")} -> Middle-aged | E73: 2n Cycle | F73: Married | H73: =IF(G73=0,MEDIAN(Income),G73) -> 51371 | I73: {=_xlfn.IFS(H73<PERCENTILE(Income_Clean,0.33),"Low",H73<PERCENTILE(Income_Clean,0.67),"Medium",H73>PERCENTILE(Income_Clean,0.67),"High")} -> Medium | J73: =_xlfn.XLOOKUP(I73,$AK$3:$AK$5,$AL$3:$AL$5) -> Average Income | K73: 1 | L73: 0 | M73: =IF(K73+L73>0,"Yes","No") -> Yes | N73: 2012-09-14 | O73: 25 | P73: 25 | Q73: 3 | R73: 43 | S73: 17 | T73: 4 | U73: 17 | V73: =SUM(P73:U73) -> 109 | W73: 3 | X73: 3 | Y73: 0 | Z73: 3 | AA73: 8 | AB73: 0 | AC73: 0 | AD73: 0 | AE73: 0 | AF73: 0 | AG73: =SUM(AB73:AF73) -> 0 | AH73: 0 | AI73: 0
A74: 6312 | B74: 1959 | C74: =2026-B74 -> 67 | D74: {=_xlfn.IFS(C74<36,"Young",C74<56,"Middle-aged",C74>=56,"Senior")} -> Senior | E74: Graduation | F74: Married | G74: 65031 | H74: =IF(G74=0,MEDIAN(Income),G74) -> 65031 | I74: {=_xlfn.IFS(H74<PERCENTILE(Income_Clean,0.33),"Low",H74<PERCENTILE(Income_Clean,0.67),"Medium",H74>PERCENTILE(Income_Clean,0.67),"High")} -> High | J74: =_xlfn.XLOOKUP(I74,$AK$3:$AK$5,$AL$3:$AL$5) -> Above Average Income | K74: 0 | L74: 1 | M74: =IF(K74+L74>0,"Yes","No") -> Yes | N74: 2013-03-17 | O74: 29 | P74: 258 | Q74: 107 | R74: 291 | S74: 84 | T74: 37 | U74: 86 | V74: =SUM(P74:U74) -> 863 | W74: 4 | X74: 10 | Y74: 3 | Z74: 13 | AA74: 7 | AB74: 0 | AC74: 0 | AD74: 0 | AE74: 0 | AF74: 0 | AG74: =SUM(AB74:AF74) -> 0 | AH74: 0 | AI74: 0
A75: 8132 | B75: 1975 | C75: =2026-B75 -> 51 | D75: {=_xlfn.IFS(C75<36,"Young",C75<56,"Middle-aged",C75>=56,"Senior")} -> Middle-aged | E75: PhD | F75: Married | G75: 60631 | H75: =IF(G75=0,MEDIAN(Income),G75) -> 60631 | I75: {=_xlfn.IFS(H75<PERCENTILE(Income_Clean,0.33),"Low",H75<PERCENTILE(Income_Clean,0.67),"Medium",H75>PERCENTILE(Income_Clean,0.67),"High")} -> Medium | J75: =_xlfn.XLOOKUP(I75,$AK$3:$AK$5,$AL$3:$AL$5) -> Average Income | K75: 1 | L75: 1 | M75: =IF(K75+L75>0,"Yes","No") -> Yes | N75: 2013-04-05 | O75: 88 | P75: 565 | Q75: 6 | R75: 65 | S75: 0 | T75: 6 | U75: 19 | V75: =SUM(P75:U75) -> 661 | W75: 5 | X75: 9 | Y75: 2 | Z75: 8 | AA75: 7 | AB75: 0 | AC75: 1 | AD75: 0 | AE75: 0 | AF75: 0 | AG75: =SUM(AB75:AF75) -> 1 | AH75: 0 | AI75: 0
A76: 1050 | B76: 1952 | C76: =2026-B76 -> 74 | D76: {=_xlfn.IFS(C76<36,"Young",C76<56,"Middle-aged",C76>=56,"Senior")} -> Senior | E76: Graduation | F76: Married | G76: 28332 | H76: =IF(G76=0,MEDIAN(Income),G76) -> 28332 | I76: {=_xlfn.IFS(H76<PERCENTILE(Income_Clean,0.33),"Low",H76<PERCENTILE(Income_Clean,0.67),"Medium",H76>PERCENTILE(Income_Clean,0.67),"High")} -> Low | J76: =_xlfn.XLOOKUP(I76,$AK$3:$AK$5,$AL$3:$AL$5) -> Below Average Income | K76: 0 | L76: 0 | M76: =IF(K76+L76>0,"Yes","No") -> No | N76: 2014-04-30 | O76: 58 | P76: 14 | Q76: 10 | R76: 13 | S76: 4 | T76: 15 | U76: 9 | V76: =SUM(P76:U76) -> 65 | W76: 1 | X76: 2 | Y76: 1 | Z76: 4 | AA76: 2 | AB76: 0 | AC76: 0 | AD76: 0 | AE76: 0 | AF76: 0 | AG76: =SUM(AB76:AF76) -> 0 | AH76: 0 | AI76: 0
A77: 5846 | B77: 1977 | C77: =2026-B77 -> 49 | D77: {=_xlfn.IFS(C77<36,"Young",C77<56,"Middle-aged",C77>=56,"Senior")} -> Middle-aged | E77: Graduation | F77: Divorced | G77: 40246 | H77: =IF(G77=0,MEDIAN(Income),G77) -> 40246 | I77: {=_xlfn.IFS(H77<PERCENTILE(Income_Clean,0.33),"Low",H77<PERCENTILE(Income_Clean,0.67),"Medium",H77>PERCENTILE(Income_Clean,0.67),"High")} -> Low | J77: =_xlfn.XLOOKUP(I77,$AK$3:$AK$5,$AL$3:$AL$5) -> Below Average Income | K77: 1 | L77: 0 | M77: =IF(K77+L77>0,"Yes","No") -> Yes | N77: 2012-12-19 | O77: 68 | P77: 2 | Q77: 1 | R77: 6 | S77: 2 | T77: 1 | U77: 1 | V77: =SUM(P77:U77) -> 13 | W77: 1 | X77: 1 | Y77: 0 | Z77: 2 | AA77: 6 | AB77: 0 | AC77: 0 | AD77: 0 | AE77: 0 | AF77: 0 | AG77: =SUM(AB77:AF77) -> 0 | AH77: 0 | AI77: 0
A78: 1859 | B78: 1972 | C78: =2026-B78 -> 54 | D78: {=_xlfn.IFS(C78<36,"Young",C78<56,"Middle-aged",C78>=56,"Senior")} -> Middle-aged | E78: Master | F78: Married | G78: 75251 | H78: =IF(G78=0,MEDIAN(Income),G78) -> 75251 | I78: {=_xlfn.IFS(H78<PERCENTILE(Income_Clean,0.33),"Low",H78<PERCENTILE(Income_Clean,0.67),"Medium",H78>PERCENTILE(Income_Clean,0.67),"High")} -> High | J78: =_xlfn.XLOOKUP(I78,$AK$3:$AK$5,$AL$3:$AL$5) -> Above Average Income | K78: 0 | L78: 0 | M78: =IF(K78+L78>0,"Yes","No") -> No | N78: 2012-08-27 | O78: 34 | P78: 721 | Q78: 111 | R78: 925 | S78: 97 | T78: 18 | U78: 18 | V78: =SUM(P78:U78) -> 1890 | W78: 1 | X78: 7 | Y78: 6 | Z78: 5 | AA78: 5 | AB78: 0 | AC78: 0 | AD78: 0 | AE78: 0 | AF78: 0 | AG78: =SUM(AB78:AF78) -> 0 | AH78: 0 | AI78: 1
A79: 7503 | B79: 1976 | C79: =2026-B79 -> 50 | D79: {=_xlfn.IFS(C79<36,"Young",C79<56,"Middle-aged",C79>=56,"Senior")} -> Middle-aged | E79: Graduation | F79: Single | G79: 75825 | H79: =IF(G79=0,MEDIAN(Income),G79) -> 75825 | I79: {=_xlfn.IFS(H79<PERCENTILE(Income_Clean,0.33),"Low",H79<PERCENTILE(Income_Clean,0.67),"Medium",H79>PERCENTILE(Income_Clean,0.67),"High")} -> High | J79: =_xlfn.XLOOKUP(I79,$AK$3:$AK$5,$AL$3:$AL$5) -> Above Average Income | K79: 0 | L79: 0 | M79: =IF(K79+L79>0,"Yes","No") -> No | N79: 2012-10-12 | O79: 40 | P79: 1032 | Q79: 105 | R79: 779 | S79: 137 | T79: 105 | U79: 51 | V79: =SUM(P79:U79) -> 2209 | W79: 0 | X79: 5 | Y79: 8 | Z79: 9 | AA79: 4 | AB79: 1 | AC79: 0 | AD79: 0 | AE79: 0 | AF79: 0 | AG79: =SUM(AB79:AF79) -> 1 | AH79: 0 | AI79: 1
A80: 10401 | B80: 1976 | C80: =2026-B80 -> 50 | D80: {=_xlfn.IFS(C80<36,"Young",C80<56,"Middle-aged",C80>=56,"Senior")} -> Middle-aged | E80: 2n Cycle | F80: Together | G80: 26326 | H80: =IF(G80=0,MEDIAN(Income),G80) -> 26326 | I80: {=_xlfn.IFS(H80<PERCENTILE(Income_Clean,0.33),"Low",H80<PERCENTILE(Income_Clean,0.67),"Medium",H80>PERCENTILE(Income_Clean,0.67),"High")} -> Low | J80: =_xlfn.XLOOKUP(I80,$AK$3:$AK$5,$AL$3:$AL$5) -> Below Average Income | K80: 0 | L80: 0 | M80: =IF(K80+L80>0,"Yes","No") -> No | N80: 2013-09-04 | O80: 12 | P80: 1 | Q80: 0 | R80: 5 | S80: 0 | T80: 3 | U80: 9 | V80: =SUM(P80:U80) -> 18 | W80: 1 | X80: 0 | Y80: 0 | Z80: 3 | AA80: 3 | AB80: 0 | AC80: 0 | AD80: 0 | AE80: 0 | AF80: 0 | AG80: =SUM(AB80:AF80) -> 0 | AH80: 1 | AI80: 0
A81: 1618 | B81: 1965 | C81: =2026-B81 -> 61 | D81: {=_xlfn.IFS(C81<36,"Young",C81<56,"Middle-aged",C81>=56,"Senior")} -> Senior | E81: Graduation | F81: Together | G81: 56046 | H81: =IF(G81=0,MEDIAN(Income),G81) -> 56046 | I81: {=_xlfn.IFS(H81<PERCENTILE(Income_Clean,0.33),"Low",H81<PERCENTILE(Income_Clean,0.67),"Medium",H81>PERCENTILE(Income_Clean,0.67),"High")} -> Medium | J81: =_xlfn.XLOOKUP(I81,$AK$3:$AK$5,$AL$3:$AL$5) -> Average Income | K81: 0 | L81: 0 | M81: =IF(K81+L81>0,"Yes","No") -> No | N81: 2013-01-02 | O81: 9 | P81: 577 | Q81: 0 | R81: 64 | S81: 0 | T81: 0 | U81: 51 | V81: =SUM(P81:U81) -> 692 | W81: 2 | X81: 10 | Y81: 1 | Z81: 8 | AA81: 8 | AB81: 1 | AC81: 0 | AD81: 0 | AE81: 0 | AF81: 0 | AG81: =SUM(AB81:AF81) -> 1 | AH81: 0 | AI81: 1
A82: 3332 | B82: 1985 | C82: =2026-B82 -> 41 | D82: {=_xlfn.IFS(C82<36,"Young",C82<56,"Middle-aged",C82>=56,"Senior")} -> Middle-aged | E82: Graduation | F82: Single | G82: 29760 | H82: =IF(G82=0,MEDIAN(Income),G82) -> 29760 | I82: {=_xlfn.IFS(H82<PERCENTILE(Income_Clean,0.33),"Low",H82<PERCENTILE(Income_Clean,0.67),"Medium",H82>PERCENTILE(Income_Clean,0.67),"High")} -> Low | J82: =_xlfn.XLOOKUP(I82,$AK$3:$AK$5,$AL$3:$AL$5) -> Below Average Income | K82: 1 | L82: 0 | M82: =IF(K82+L82>0,"Yes","No") -> Yes | N82: 2012-08-29 | O82: 87 | P82: 64 | Q82: 4 | R82: 68 | S82: 7 | T82: 5 | U82: 17 | V82: =SUM(P82:U82) -> 165 | W82: 4 | X82: 3 | Y82: 1 | Z82: 4 | AA82: 8 | AB82: 0 | AC82: 0 | AD82: 0 | AE82: 0 | AF82: 0 | AG82: =SUM(AB82:AF82) -> 0 | AH82: 0 | AI82: 0
A83: 2261 | B83: 1969 | C83: =2026-B83 -> 57 | D83: {=_xlfn.IFS(C83<36,"Young",C83<56,"Middle-aged",C83>=56,"Senior")} -> Senior | E83: Graduation | F83: Married | G83: 26304 | H83: =IF(G83=0,MEDIAN(Income),G83) -> 26304 | I83: {=_xlfn.IFS(H83<PERCENTILE(Income_Clean,0.33),"Low",H83<PERCENTILE(Income_Clean,0.67),"Medium",H83>PERCENTILE(Income_Clean,0.67),"High")} -> Low | J83: =_xlfn.XLOOKUP(I83,$AK$3:$AK$5,$AL$3:$AL$5) -> Below Average Income | K83: 1 | L83: 0 | M83: =IF(K83+L83>0,"Yes","No") -> Yes | N83: 2013-06-23 | O83: 5 | P83: 4 | Q83: 1 | R83: 5 | S83: 2 | T83: 0 | U83: 4 | V83: =SUM(P83:U83) -> 16 | W83: 1 | X83: 1 | Y83: 0 | Z83: 2 | AA83: 7 | AB83: 0 | AC83: 0 | AD83: 0 | AE83: 0 | AF83: 0 | AG83: =SUM(AB83:AF83) -> 0 | AH83: 0 | AI83: 0
A84: 5346 | B84: 1973 | C84: =2026-B84 -> 53 | D84: {=_xlfn.IFS(C84<36,"Young",C84<56,"Middle-aged",C84>=56,"Senior")} -> Middle-aged | E84: 2n Cycle | F84: Married | G84: 23559 | H84: =IF(G84=0,MEDIAN(Income),G84) -> 23559 | I84: {=_xlfn.IFS(H84<PERCENTILE(Income_Clean,0.33),"Low",H84<PERCENTILE(Income_Clean,0.67),"Medium",H84>PERCENTILE(Income_Clean,0.67),"High")} -> Low | J84: =_xlfn.XLOOKUP(I84,$AK$3:$AK$5,$AL$3:$AL$5) -> Below Average Income | K84: 1 | L84: 0 | M84: =IF(K84+L84>0,"Yes","No") -> Yes | N84: 2013-07-03 | O84: 87 | P84: 25 | Q84: 5 | R84: 19 | S84: 7 | T84: 0 | U84: 23 | V84: =SUM(P84:U84) -> 79 | W84: 3 | X84: 3 | Y84: 0 | Z84: 3 | AA84: 7 | AB84: 0 | AC84: 0 | AD84: 0 | AE84: 0 | AF84: 0 | AG84: =SUM(AB84:AF84) -> 0 | AH84: 0 | AI84: 0
A85: 4119 | B85: 1963 | C85: =2026-B85 -> 63 | D85: {=_xlfn.IFS(C85<36,"Young",C85<56,"Middle-aged",C85>=56,"Senior")} -> Senior | E85: Master | F85: Together | G85: 38620 | H85: =IF(G85=0,MEDIAN(Income),G85) -> 38620 | I85: {=_xlfn.IFS(H85<PERCENTILE(Income_Clean,0.33),"Low",H85<PERCENTILE(Income_Clean,0.67),"Medium",H85>PERCENTILE(Income_Clean,0.67),"High")} -> Low | J85: =_xlfn.XLOOKUP(I85,$AK$3:$AK$5,$AL$3:$AL$5) -> Below Average Income | K85: 0 | L85: 0 | M85: =IF(K85+L85>0,"Yes","No") -> No | N85: 2013-05-11 | O85: 56 | P85: 112 | Q85: 17 | R85: 44 | S85: 34 | T85: 22 | U85: 89 | V85: =SUM(P85:U85) -> 318 | W85: 1 | X85: 2 | Y85: 5 | Z85: 3 | AA85: 3 | AB85: 0 | AC85: 0 | AD85: 0 | AE85: 0 | AF85: 0 | AG85: =SUM(AB85:AF85) -> 0 | AH85: 0 | AI85: 0
... A91: 771 | B91: 1967 | C91: =2026-B91 -> 59 | D91: {=_xlfn.IFS(C91<36,"Young",C91<56,"Middle-aged",C91>=56,"Senior")} -> Senior | E91: Graduation | F91: Together | G91: 54178 | H91: =IF(G91=0,MEDIAN(Income),G91) -> 54178 | I91: {=_xlfn.IFS(H91<PERCENTILE(Income_Clean,0.33),"Low",H91<PERCENTILE(Income_Clean,0.67),"Medium",H91>PERCENTILE(Income_Clean,0.67),"High")} -> Medium | J91: =_xlfn.XLOOKUP(I91,$AK$3:$AK$5,$AL$3:$AL$5) -> Average Income | K91: 0 | L91: 1 | M91: =IF(K91+L91>0,"Yes","No") -> Yes | N91: 2014-01-21 | O91: 79 | P91: 135 | Q91: 9 | R91: 39 | S91: 4 | T91: 0 | U91: 7 | V91: =SUM(P91:U91) -> 194 | W91: 1 | X91: 2 | Y91: 2 | Z91: 5 | AA91: 2 | AB91: 0 | AC91: 0 | AD91: 0 | AE91: 0 | AF91: 0 | AG91: =SUM(AB91:AF91) -> 0 | AH91: 0 | AI91: 0
A92: 8996 | B92: 1957 | C92: =2026-B92 -> 69 | D92: {=_xlfn.IFS(C92<36,"Young",C92<56,"Middle-aged",C92>=56,"Senior")} -> Senior | E92: PhD | F92: Married | H92: =IF(G92=0,MEDIAN(Income),G92) -> 51371 | I92: {=_xlfn.IFS(H92<PERCENTILE(Income_Clean,0.33),"Low",H92<PERCENTILE(Income_Clean,0.67),"Medium",H92>PERCENTILE(Income_Clean,0.67),"High")} -> Medium | J92: =_xlfn.XLOOKUP(I92,$AK$3:$AK$5,$AL$3:$AL$5) -> Average Income | K92: 2 | L92: 1 | M92: =IF(K92+L92>0,"Yes","No") -> Yes | N92: 2012-11-19 | O92: 4 | P92: 230 | Q92: 42 | R92: 192 | S92: 49 | T92: 37 | U92: 53 | V92: =SUM(P92:U92) -> 603 | W92: 12 | X92: 7 | Y92: 2 | Z92: 8 | AA92: 9 | AB92: 0 | AC92: 0 | AD92: 0 | AE92: 0 | AF92: 0 | AG92: =SUM(AB92:AF92) -> 0 | AH92: 0 | AI92: 0
A93: 9235 | B93: 1957 | C93: =2026-B93 -> 69 | D93: {=_xlfn.IFS(C93<36,"Young",C93<56,"Middle-aged",C93>=56,"Senior")} -> Senior | E93: Graduation | F93: Single | H93: =IF(G93=0,MEDIAN(Income),G93) -> 51371 | I93: {=_xlfn.IFS(H93<PERCENTILE(Income_Clean,0.33),"Low",H93<PERCENTILE(Income_Clean,0.67),"Medium",H93>PERCENTILE(Income_Clean,0.67),"High")} -> Medium | J93: =_xlfn.XLOOKUP(I93,$AK$3:$AK$5,$AL$3:$AL$5) -> Average Income | K93: 1 | L93: 1 | M93: =IF(K93+L93>0,"Yes","No") -> Yes | N93: 2014-05-27 | O93: 45 | P93: 7 | Q93: 0 | R93: 8 | S93: 2 | T93: 0 | U93: 1 | V93: =SUM(P93:U93) -> 18 | W93: 1 | X93: 1 | Y93: 0 | Z93: 2 | AA93: 7 | AB93: 0 | AC93: 0 | AD93: 0 | AE93: 0 | AF93: 0 | AG93: =SUM(AB93:AF93) -> 0 | AH93: 0 | AI93: 0
A94: 5798 | B94: 1973 | C94: =2026-B94 -> 53 | D94: {=_xlfn.IFS(C94<36,"Young",C94<56,"Middle-aged",C94>=56,"Senior")} -> Middle-aged | E94: Master | F94: Together | H94: =IF(G94=0,MEDIAN(Income),G94) -> 51371 | I94: {=_xlfn.IFS(H94<PERCENTILE(Income_Clean,0.33),"Low",H94<PERCENTILE(Income_Clean,0.67),"Medium",H94>PERCENTILE(Income_Clean,0.67),"High")} -> Medium | J94: =_xlfn.XLOOKUP(I94,$AK$3:$AK$5,$AL$3:$AL$5) -> Average Income | K94: 0 | L94: 0 | M94: =IF(K94+L94>0,"Yes","No") -> No | N94: 2013-11-23 | O94: 87 | P94: 445 | Q94: 37 | R94: 359 | S94: 98 | T94: 28 | U94: 18 | V94: =SUM(P94:U94) -> 985 | W94: 1 | X94: 2 | Y94: 4 | Z94: 8 | AA94: 1 | AB94: 0 | AC94: 0 | AD94: 0 | AE94: 0 | AF94: 0 | AG94: =SUM(AB94:AF94) -> 0 | AH94: 0 | AI94: 0
A95: 11178 | B95: 1972 | C95: =2026-B95 -> 54 | D95: {=_xlfn.IFS(C95<36,"Young",C95<56,"Middle-aged",C95>=56,"Senior")} -> Middle-aged | E95: Master | F95: Single | G95: 42394 | H95: =IF(G95=0,MEDIAN(Income),G95) -> 42394 | I95: {=_xlfn.IFS(H95<PERCENTILE(Income_Clean,0.33),"Low",H95<PERCENTILE(Income_Clean,0.67),"Medium",H95>PERCENTILE(Income_Clean,0.67),"High")} -> Medium | J95: =_xlfn.XLOOKUP(I95,$AK$3:$AK$5,$AL$3:$AL$5) -> Average Income | K95: 1 | L95: 0 | M95: =IF(K95+L95>0,"Yes","No") -> Yes | N95: 2014-03-23 | O95: 69 | P95: 15 | Q95: 2 | R95: 10 | S95: 0 | T95: 1 | U95: 4 | V95: =SUM(P95:U95) -> 32 | W95: 1 | X95: 1 | Y95: 0 | Z95: 3 | AA95: 7 | AB95: 0 | AC95: 0 | AD95: 0 | AE95: 0 | AF95: 0 | AG95: =SUM(AB95:AF95) -> 0 | AH95: 0 | AI95: 0
A96: 2230 | B96: 1970 | C96: =2026-B96 -> 56 | D96: {=_xlfn.IFS(C96<36,"Young",C96<56,"Middle-aged",C96>=56,"Senior")} -> Senior | E96: PhD | F96: Married | G96: 23626 | H96: =IF(G96=0,MEDIAN(Income),G96) -> 23626 | I96: {=_xlfn.IFS(H96<PERCENTILE(Income_Clean,0.33),"Low",H96<PERCENTILE(Income_Clean,0.67),"Medium",H96>PERCENTILE(Income_Clean,0.67),"High")} -> Low | J96: =_xlfn.XLOOKUP(I96,$AK$3:$AK$5,$AL$3:$AL$5) -> Below Average Income | K96: 1 | L96: 0 | M96: =IF(K96+L96>0,"Yes","No") -> Yes | N96: 2014-05-24 | O96: 84 | P96: 27 | Q96: 2 | R96: 14 | S96: 0 | T96: 0 | U96: 0 | V96: =SUM(P96:U96) -> 43 | W96: 3 | X96: 3 | Y96: 1 | Z96: 3 | AA96: 5 | AB96: 0 | AC96: 0 | AD96: 0 | AE96: 0 | AF96: 0 | AG96: =SUM(AB96:AF96) -> 0 | AH96: 0 | AI96: 0
A97: 7516 | B97: 1983 | C97: =2026-B97 -> 43 | D97: {=_xlfn.IFS(C97<36,"Young",C97<56,"Middle-aged",C97>=56,"Senior")} -> Middle-aged | E97: Graduation | F97: Married | G97: 30096 | H97: =IF(G97=0,MEDIAN(Income),G97) -> 30096 | I97: {=_xlfn.IFS(H97<PERCENTILE(Income_Clean,0.33),"Low",H97<PERCENTILE(Income_Clean,0.67),"Medium",H97>PERCENTILE(Income_Clean,0.67),"High")} -> Low | J97: =_xlfn.XLOOKUP(I97,$AK$3:$AK$5,$AL$3:$AL$5) -> Below Average Income | K97: 1 | L97: 0 | M97: =IF(K97+L97>0,"Yes","No") -> Yes | N97: 2014-05-22 | O97: 30 | P97: 5 | Q97: 3 | R97: 11 | S97: 12 | T97: 5 | U97: 9 | V97: =SUM(P97:U97) -> 45 | W97: 1 | X97: 2 | Y97: 0 | Z97: 3 | AA97: 6 | AB97: 0 | AC97: 0 | AD97: 0 | AE97: 0 | AF97: 0 | AG97: =SUM(AB97:AF97) -> 0 | AH97: 0 | AI97: 0
A98: 7247 | B98: 1960 | C98: =2026-B98 -> 66 | D98: {=_xlfn.IFS(C98<36,"Young",C98<56,"Middle-aged",C98>=56,"Senior")} -> Senior | E98: Graduation | F98: Widow | G98: 47916 | H98: =IF(G98=0,MEDIAN(Income),G98) -> 47916 | I98: {=_xlfn.IFS(H98<PERCENTILE(Income_Clean,0.33),"Low",H98<PERCENTILE(Income_Clean,0.67),"Medium",H98>PERCENTILE(Income_Clean,0.67),"High")} -> Medium | J98: =_xlfn.XLOOKUP(I98,$AK$3:$AK$5,$AL$3:$AL$5) -> Average Income | K98: 0 | L98: 1 | M98: =IF(K98+L98>0,"Yes","No") -> Yes | N98: 2012-11-22 | O98: 72 | P98: 505 | Q98: 0 | R98: 26 | S98: 0 | T98: 0 | U98: 75 | V98: =SUM(P98:U98) -> 606 | W98: 5 | X98: 7 | Y98: 4 | Z98: 6 | AA98: 6 | AB98: 0 | AC98: 1 | AD98: 0 | AE98: 0 | AF98: 0 | AG98: =SUM(AB98:AF98) -> 1 | AH98: 0 | AI98: 0
A99: 11100 | B99: 1972 | C99: =2026-B99 -> 54 | D99: {=_xlfn.IFS(C99<36,"Young",C99<56,"Middle-aged",C99>=56,"Senior")} -> Middle-aged | E99: Graduation | F99: Divorced | G99: 51813 | H99: =IF(G99=0,MEDIAN(Income),G99) -> 51813 | I99: {=_xlfn.IFS(H99<PERCENTILE(Income_Clean,0.33),"Low",H99<PERCENTILE(Income_Clean,0.67),"Medium",H99>PERCENTILE(Income_Clean,0.67),"High")} -> Medium | J99: =_xlfn.XLOOKUP(I99,$AK$3:$AK$5,$AL$3:$AL$5) -> Average Income | K99: 1 | L99: 1 | M99: =IF(K99+L99>0,"Yes","No") -> Yes | N99: 2013-04-11 | O99: 37 | P99: 51 | Q99: 2 | R99: 7 | S99: 0 | T99: 1 | U99: 2 | V99: =SUM(P99:U99) -> 63 | W99: 2 | X99: 2 | Y99: 0 | Z99: 3 | AA99: 7 | AB99: 0 | AC99: 0 | AD99: 0 | AE99: 0 | AF99: 0 | AG99: =SUM(AB99:AF99) -> 0 | AH99: 0 | AI99: 0
A100: 4646 | B100: 1951 | C100: =2026-B100 -> 75 | D100: {=_xlfn.IFS(C100<36,"Young",C100<56,"Middle-aged",C100>=56,"Senior")} -> Senior | E100: 2n Cycle | F100: Married | G100: 78497 | H100: =IF(G100=0,MEDIAN(Income),G100) -> 78497 | I100: {=_xlfn.IFS(H100<PERCENTILE(Income_Clean,0.33),"Low",H100<PERCENTILE(Income_Clean,0.67),"Medium",H100>PERCENTILE(Income_Clean,0.67),"High")} -> High | J100: =_xlfn.XLOOKUP(I100,$AK$3:$AK$5,$AL$3:$AL$5) -> Above Average Income | K100: 0 | L100: 0 | M100: =IF(K100+L100>0,"Yes","No") -> No | N100: 2013-12-01 | O100: 44 | P100: 207 | Q100: 26 | R100: 447 | S100: 75 | T100: 0 | U100: 223 | V100: =SUM(P100:U100) -> 978 | W100: 1 | X100: 5 | Y100: 7 | Z100: 12 | AA100: 2 | AB100: 0 | AC100: 0 | AD100: 0 | AE100: 1 | AF100: 0 | AG100: =SUM(AB100:AF100) -> 1 | AH100: 0 | AI100: 0
A101: 3037 | B101: 1983 | C101: =2026-B101 -> 43 | D101: {=_xlfn.IFS(C101<36,"Young",C101<56,"Middle-aged",C101>=56,"Senior")} -> Middle-aged | E101: PhD | F101: Married | G101: 50150 | H101: =IF(G101=0,MEDIAN(Income),G101) -> 50150 | I101: {=_xlfn.IFS(H101<PERCENTILE(Income_Clean,0.33),"Low",H101<PERCENTILE(Income_Clean,0.67),"Medium",H101>PERCENTILE(Income_Clean,0.67),"High")} -> Medium | J101: =_xlfn.XLOOKUP(I101,$AK$3:$AK$5,$AL$3:$AL$5) -> Average Income | K101: 0 | L101: 0 | M101: =IF(K101+L101>0,"Yes","No") -> No | N101: 2013-06-20 | O101: 32 | P101: 135 | Q101: 46 | R101: 92 | S101: 65 | T101: 61 | U101: 11 | V101: =SUM(P101:U101) -> 410 | W101: 2 | X101: 5 | Y101: 2 | Z101: 7 | AA101: 5 | AB101: 0 | AC101: 0 | AD101: 0 | AE101: 0 | AF101: 0 | AG101: =SUM(AB101:AF101) -> 0 | AH101: 0 | AI101: 0
A102: 1473 | B102: 1960 | C102: =2026-B102 -> 66 | D102: {=_xlfn.IFS(C102<36,"Young",C102<56,"Middle-aged",C102>=56,"Senior")} -> Senior | E102: 2n Cycle | F102: Single | G102: 47823 | H102: =IF(G102=0,MEDIAN(Income),G102) -> 47823 | I102: {=_xlfn.IFS(H102<PERCENTILE(Income_Clean,0.33),"Low",H102<PERCENTILE(Income_Clean,0.67),"Medium",H102>PERCENTILE(Income_Clean,0.67),"High")} -> Medium | J102: =_xlfn.XLOOKUP(I102,$AK$3:$AK$5,$AL$3:$AL$5) -> Average Income | K102: 0 | L102: 1 | M102: =IF(K102+L102>0,"Yes","No") -> Yes | N102: 2013-07-23 | O102: 0 | P102: 53 | Q102: 1 | R102: 5 | S102: 2 | T102: 1 | U102: 10 | V102: =SUM(P102:U102) -> 72 | W102: 2 | X102: 2 | Y102: 0 | Z102: 3 | AA102: 8 | AB102: 0 | AC102: 0 | AD102: 0 | AE102: 0 | AF102: 0 | AG102: =SUM(AB102:AF102) -> 0 | AH102: 0 | AI102: 0
A103: 1016 | B103: 1959 | C103: =2026-B103 -> 67 | D103: {=_xlfn.IFS(C103<36,"Young",C103<56,"Middle-aged",C103>=56,"Senior")} -> Senior | E103: PhD | F103: Single | G103: 34554 | H103: =IF(G103=0,MEDIAN(Income),G103) -> 34554 | I103: {=_xlfn.IFS(H103<PERCENTILE(Income_Clean,0.33),"Low",H103<PERCENTILE(Income_Clean,0.67),"Medium",H103>PERCENTILE(Income_Clean,0.67),"High")} -> Low | J103: =_xlfn.XLOOKUP(I103,$AK$3:$AK$5,$AL$3:$AL$5) -> Below Average Income | K103: 0 | L103: 1 | M103: =IF(K103+L103>0,"Yes","No") -> Yes | N103: 2014-03-30 | O103: 43 | P103: 41 | Q103: 1 | R103: 6 | S103: 2 | T103: 0 | U103: 5 | V103: =SUM(P103:U103) -> 55 | W103: 2 | X103: 2 | Y103: 0 | Z103: 3 | AA103: 6 | AB103: 0 | AC103: 0 | AD103: 0 | AE103: 0 | AF103: 0 | AG103: =SUM(AB103:AF103) -> 0 | AH103: 0 | AI103: 0
A104: 4518 | B104: 1979 | C104: =2026-B104 -> 47 | D104: {=_xlfn.IFS(C104<36,"Young",C104<56,"Middle-aged",C104>=56,"Senior")} -> Middle-aged | E104: Graduation | F104: Together | G104: 85693 | H104: =IF(G104=0,MEDIAN(Income),G104) -> 85693 | I104: {=_xlfn.IFS(H104<PERCENTILE(Income_Clean,0.33),"Low",H104<PERCENTILE(Income_Clean,0.67),"Medium",H104>PERCENTILE(Income_Clean,0.67),"High")} -> High | J104: =_xlfn.XLOOKUP(I104,$AK$3:$AK$5,$AL$3:$AL$5) -> Above Average Income | K104: 0 | L104: 1 | M104: =IF(K104+L104>0,"Yes","No") -> Yes | N104: 2013-04-20 | O104: 59 | P104: 386 | Q104: 172 | R104: 183 | S104: 185 | T104: 132 | U104: 111 | V104: =SUM(P104:U104) -> 1169 | W104: 2 | X104: 9 | Y104: 5 | Z104: 11 | AA104: 5 | AB104: 0 | AC104: 0 | AD104: 0 | AE104: 0 | AF104: 0 | AG104: =SUM(AB104:AF104) -> 0 | AH104: 0 | AI104: 0
A105: 9370 | B105: 1945 | C105: =2026-B105 -> 81 | D105: {=_xlfn.IFS(C105<36,"Young",C105<56,"Middle-aged",C105>=56,"Senior")} -> Senior | E105: PhD | F105: Married | G105: 65846 | H105: =IF(G105=0,MEDIAN(Income),G105) -> 65846 | I105: {=_xlfn.IFS(H105<PERCENTILE(Income_Clean,0.33),"Low",H105<PERCENTILE(Income_Clean,0.67),"Medium",H105>PERCENTILE(Income_Clean,0.67),"High")} -> High | J105: =_xlfn.XLOOKUP(I105,$AK$3:$AK$5,$AL$3:$AL$5) -> Above Average Income | K105: 0 | L105: 0 | M105: =IF(K105+L105>0,"Yes","No") -> No | N105: 2013-05-17 | O105: 68 | P105: 562 | Q105: 81 | R105: 276 | S105: 80 | T105: 40 | U105: 81 | V105: =SUM(P105:U105) -> 1120 | W105: 1 | X105: 6 | Y105: 3 | Z105: 6 | AA105: 4 | AB105: 0 | AC105: 0 | AD105: 0 | AE105: 0 | AF105: 0 | AG105: =SUM(AB105:AF105) -> 0 | AH105: 0 | AI105: 0
A106: 8908 | B106: 1959 | C106: =2026-B106 -> 67 | D106: {=_xlfn.IFS(C106<36,"Young",C106<56,"Middle-aged",C106>=56,"Senior")} -> Senior | E106: Graduation | F106: Married | G106: 87195 | H106: =IF(G106=0,MEDIAN(Income),G106) -> 87195 | I106: {=_xlfn.IFS(H106<PERCENTILE(Income_Clean,0.33),"Low",H106<PERCENTILE(Income_Clean,0.67),"Medium",H106>PERCENTILE(Income_Clean,0.67),"High")} -> High | J106: =_xlfn.XLOOKUP(I106,$AK$3:$AK$5,$AL$3:$AL$5) -> Above Average Income | K106: 0 | L106: 0 | M106: =IF(K106+L106>0,"Yes","No") -> No | N106: 2014-05-08 | O106: 35 | P106: 217 | Q106: 76 | R106: 690 | S106: 50 | T106: 26 | U106: 38 | V106: =SUM(P106:U106) -> 1097 | W106: 1 | X106: 3 | Y106: 11 | Z106: 5 | AA106: 1 | AB106: 0 | AC106: 0 | AD106: 0 | AE106: 0 | AF106: 0 | AG106: =SUM(AB106:AF106) -> 0 | AH106: 0 | AI106: 1
... A129: 3381 | B129: 1953 | C129: =2026-B129 -> 73 | D129: {=_xlfn.IFS(C129<36,"Young",C129<56,"Middle-aged",C129>=56,"Senior")} -> Senior | E129: Master | F129: Married | G129: 54348 | H129: =IF(G129=0,MEDIAN(Income),G129) -> 54348 | I129: {=_xlfn.IFS(H129<PERCENTILE(Income_Clean,0.33),"Low",H129<PERCENTILE(Income_Clean,0.67),"Medium",H129>PERCENTILE(Income_Clean,0.67),"High")} -> Medium | J129: =_xlfn.XLOOKUP(I129,$AK$3:$AK$5,$AL$3:$AL$5) -> Average Income | K129: 1 | L129: 1 | M129: =IF(K129+L129>0,"Yes","No") -> Yes | N129: 2014-06-08 | O129: 51 | P129: 70 | Q129: 0 | R129: 16 | S129: 0 | T129: 0 | U129: 4 | V129: =SUM(P129:U129) -> 90 | W129: 2 | X129: 2 | Y129: 0 | Z129: 4 | AA129: 6 | AB129: 0 | AC129: 0 | AD129: 0 | AE129: 0 | AF129: 0 | AG129: =SUM(AB129:AF129) -> 0 | AH129: 0 | AI129: 0
A130: 8268 | B130: 1961 | C130: =2026-B130 -> 65 | D130: {=_xlfn.IFS(C130<36,"Young",C130<56,"Middle-aged",C130>=56,"Senior")} -> Senior | E130: PhD | F130: Married | H130: =IF(G130=0,MEDIAN(Income),G130) -> 51371 | I130: {=_xlfn.IFS(H130<PERCENTILE(Income_Clean,0.33),"Low",H130<PERCENTILE(Income_Clean,0.67),"Medium",H130>PERCENTILE(Income_Clean,0.67),"High")} -> Medium | J130: =_xlfn.XLOOKUP(I130,$AK$3:$AK$5,$AL$3:$AL$5) -> Average Income | K130: 0 | L130: 1 | M130: =IF(K130+L130>0,"Yes","No") -> Yes | N130: 2013-07-11 | O130: 23 | P130: 352 | Q130: 0 | R130: 27 | S130: 10 | T130: 0 | U130: 15 | V130: =SUM(P130:U130) -> 404 | W130: 3 | X130: 6 | Y130: 1 | Z130: 7 | AA130: 6 | AB130: 0 | AC130: 0 | AD130: 0 | AE130: 0 | AF130: 0 | AG130: =SUM(AB130:AF130) -> 0 | AH130: 0 | AI130: 0
A131: 11051 | B131: 1956 | C131: =2026-B131 -> 70 | D131: {=_xlfn.IFS(C131<36,"Young",C131<56,"Middle-aged",C131>=56,"Senior")} -> Senior | E131: PhD | F131: Together | G131: 77376 | H131: =IF(G131=0,MEDIAN(Income),G131) -> 77376 | I131: {=_xlfn.IFS(H131<PERCENTILE(Income_Clean,0.33),"Low",H131<PERCENTILE(Income_Clean,0.67),"Medium",H131>PERCENTILE(Income_Clean,0.67),"High")} -> High | J131: =_xlfn.XLOOKUP(I131,$AK$3:$AK$5,$AL$3:$AL$5) -> Above Average Income | K131: 1 | L131: 1 | M131: =IF(K131+L131>0,"Yes","No") -> Yes | N131: 2014-05-10 | O131: 72 | P131: 492 | Q131: 19 | R131: 110 | S131: 16 | T131: 12 | U131: 12 | V131: =SUM(P131:U131) -> 661 | W131: 4 | X131: 6 | Y131: 3 | Z131: 10 | AA131: 4 | AB131: 0 | AC131: 0 | AD131: 0 | AE131: 0 | AF131: 0 | AG131: =SUM(AB131:AF131) -> 0 | AH131: 0 | AI131: 0
A132: 8026 | B132: 1952 | C132: =2026-B132 -> 74 | D132: {=_xlfn.IFS(C132<36,"Young",C132<56,"Middle-aged",C132>=56,"Senior")} -> Senior | E132: Graduation | F132: Married | G132: 62998 | H132: =IF(G132=0,MEDIAN(Income),G132) -> 62998 | I132: {=_xlfn.IFS(H132<PERCENTILE(Income_Clean,0.33),"Low",H132<PERCENTILE(Income_Clean,0.67),"Medium",H132>PERCENTILE(Income_Clean,0.67),"High")} -> High | J132: =_xlfn.XLOOKUP(I132,$AK$3:$AK$5,$AL$3:$AL$5) -> Above Average Income | K132: 0 | L132: 1 | M132: =IF(K132+L132>0,"Yes","No") -> Yes | N132: 2013-09-30 | O132: 10 | P132: 120 | Q132: 58 | R132: 73 | S132: 65 | T132: 89 | U132: 58 | V132: =SUM(P132:U132) -> 463 | W132: 5 | X132: 5 | Y132: 4 | Z132: 5 | AA132: 5 | AB132: 0 | AC132: 0 | AD132: 0 | AE132: 0 | AF132: 0 | AG132: =SUM(AB132:AF132) -> 0 | AH132: 0 | AI132: 0
...

Sheet Typical Client
A1: Who is our typical client?
A3: Age_Group | B3: Count | C3: %
A4: Senior | B4: 1150 | C4: 0.51532569 | L4: The customer base is heavily concentrated in the Senior segment (56+), making this group critical for retention and campaign performance.
A5: Middle-aged | B5: 1043 | C5: 0.46470355
A6: Young | B6: 43 | C6: 0.019970756
A25: Education | B25: Count | C25: %
A26: Graduation | B26: 1126 | C26: 0.50357782 | L26: Over 50% of customers hold a university degree (Graduation level).
A27: PhD | B27: 485 | C27: 0.21690519
A28: Master | B28: 370 | C28: 0.16547406
A29: 2n Cycle | B29: 201 | C29: 0.089892665
A30: Basic | B30: 54 | C30: 0.024150268
A43: Marital_Status | B43: Count | C43: %
A44: Married | B44: 864 | C44: 0.38640429 | L44: Most of the customers are married.
A45: Together | B45: 578 | C45: 0.25849732
A46: Single | B46: 482 | C46: 0.21556351
A47: Divorced | B47: 231 | C47: 0.10330948
A48: Widow | B48: 77 | C48: 0.034436494
A49: Unknown | B49: 4 | C49: 0.0017889088
A62: Age_Group | B62: Average of Income_Clean
A63: Middle-aged | B63: 47637.013 | L63: Income levels are fairly consistent across age groups, with Middle-aged customers earning slightly less on average (€47,637 vs €55,644 for Seniors).
A64: Senior | B64: 55644.729
A65: Young | B65: 57882.558
A81: Category | B81: Avg Spend | C81: %
A82: MntWines | B82: =AVERAGE(MntWines) -> 304.12746 | C82: =B82/SUM(Avg_Spend_Category[Avg Spend]) -> 0.50187161
A83: MntMeatProducts | B83: =AVERAGE(MntMeatProducts) -> 166.98345 | C83: =B83/SUM(Avg_Spend_Category[Avg Spend]) -> 0.27555635 | H83: Wine dominates customer spending, accounting for nearly 50% of total product expenditure, followed by meat products.
A84: MntGoldProds | B84: =AVERAGE(MntGoldProds) -> 43.983005 | C84: =B84/SUM(Avg_Spend_Category[Avg Spend]) -> 0.072580824 | H84: Wine products should be prioritized in promotional campaigns and loyalty programs.
A85: MntFishProducts | B85: =AVERAGE(MntFishProducts) -> 37.536225 | C85: =B85/SUM(Avg_Spend_Category[Avg Spend]) -> 0.061942337
A86: MntSweetProducts | B86: =AVERAGE(MntSweetProducts) -> 27.080501 | C86: =B86/SUM(Avg_Spend_Category[Avg Spend]) -> 0.044688285
A87: MntFruits | B87: =AVERAGE(MntFruits) -> 26.275939 | C87: =B87/SUM(Avg_Spend_Category[Avg Spend]) -> 0.043360596
A103: Segment | B103: Responded | C103: %
A104: Senior + High Income | B104: =COUNTIFS(Age_Group,"Senior",Income_Segment,"High",Response,1) -> 92 | C104: =B104/(B104+B105) -> 0.77310924
A105: Middle-aged + High Income | B105: =COUNTIFS(Age_Group,"Middle-aged",Income_Segment,"Medium",Response,1) -> 27 | C105: =B105/(B104+B105) -> 0.22689076
A123: Among high-income customers, Seniors represent the dominant group (77%), making them the most valuable target audience for premium campaigns.

Sheet Campaign Analysis
A1: Who will respond to an offer for a product or service?
A3: Campaign | B3: Response Rate
A4: Campaign 4 | B4: =AVERAGE(AcceptedCmp4) -> 0.074686941
A5: Campaign 3 | B5: =AVERAGE(AcceptedCmp3) -> 0.072898032
A6: Campaign 5 | B6: =AVERAGE(AcceptedCmp5) -> 0.072450805
A7: Campaign 1 | B7: =AVERAGE(AcceptedCmp1) -> 0.064400716
A8: Campaign 2 | B8: =AVERAGE(AcceptedCmp2) -> 0.013416816
A14: Campaign 2 significantly underperformed. Campaign 4 achieved the highest response rate.
A21: Avg expenses of those who accepted the offer in the last campaign | B21: =AVERAGEIF(Response,1,TotalSpend) -> 987.39222
A22: Avg expenses of those who didn't accept the offer in the last campaign | B22: =AVERAGEIF(Response,0,TotalSpend) -> 539.00999
A24: Customers who responded spent more than twice as much as those who didn't - suggesting high-value customers are more campaign-responsive.
A26: Avg income of those who accepted the offer in the last campaign | B26: =AVERAGEIF(Response,1,Income) -> 60209.676
A27: Avg income of those who didn't accept the offer in the last campaign | B27: =AVERAGEIF(Response,0,Income) -> 50496.576
A29: Average income of those who responded is also higher.
A33: Age_Group | B33: Average of Response
A34: Young | B34: 0.23255814
A35: Middle-aged | B35: 0.15340364
A36: Senior | B36: 0.1426087
A49: Young people tend to respond better to the marketing campaign.
A52: Education | B52: Average of Response
A53: PhD | B53: 0.20824742
A54: Master | B54: 0.15405405
A55: Graduation | B55: 0.13499112
A56: 2n Cycle | B56: 0.10945274
A57: Basic | B57: 0.037037037
A67: Doctors of Philosophy respond more often to a marketing campaign.
A69: Total_Campaigns | B69: Average of Response
A70: 4 | B70: 0.90909091
A71: 3 | B71: 0.79545455
A72: 2 | B72: 0.5060241
A73: 1 | B73: 0.3117284
A74: 0 | B74: 0.082299887
A85: Customers who previously agreed to a marketing campaign, in most cases agree again.
A88: Weighted average spend of customers who accepted at least 2 campaigns:
A89: {=SUMPRODUCT((TotalCampaigns>=2)*TotalSpend) / SUMPRODUCT((TotalCampaigns>=2)*1)} -> 1510.3913

Sheet Channel Analysis
A1: Where and how do customers buy?
A3: Average of NumStorePurchases | B3: Average of NumWebPurchases | C3: Average of NumCatalogPurchases | D3: Average of NumDealsPurchases
A4: =AVERAGE(NumStorePurchases) -> 5.7956172 | B4: =AVERAGE(NumWebPurchases) -> 4.0876565 | C4: =AVERAGE(NumCatalogPurchases) -> 2.6632379 | D4: =AVERAGE(NumDealsPurchases) -> 2.3260286
D10: Physical stores remain the primary sales channel, suggesting that in-store promotions can achieve the broadest customer reach.
A22: Age_Group | B22: Average of NumWebPurchases
A23: Senior | B23: 4.4721739
A24: Middle-aged | B24: 3.6816874
A25: Young | B25: 3.6511628
A38: Surprisingly, Senior customers lead in online purchases (avg. 4.47 per period), outpacing Young customers (3.65) - suggesting digital adoption among older segments is stronger than expected.
A40: Avg of purchases made with discount by those who accepted the offer in the last campaign | B40: Avg of purchases made with discount by those who didn't accept the offer in the last campaign
A41: =AVERAGEIF(Response,1,NumDealsPurchases) -> 2.3353293 | B41: =AVERAGEIF(Response,0,NumDealsPurchases) -> 2.3243954
A48: There's almost no difference between purchases made with discount
A49: by those who responded in the last campaign and who didn't.
A53: Age_Group | B53: Average of NumWebVisitsMonth
A54: Middle-aged | B54: 5.6605944
A55: Senior | B55: 5.0417391
A56: Young | B56: 4.4418605
A61: People of middle and older age tend to visit
A62: the website more often than young people.

Sheet Dashboard Analysis
A1: Overall Response Rate (%) | B1: Response | C1: 1 | D1: Response | E1: 0 | F1: Customers in Segment | G1: Best Performing Campaign (%)
A2: 0.14937388 | F2: 2236 | G2: 0.074686941
B3: Avg. Spend of Responders ($) | D3: Avg. Spend of Responders ($)
B4: 987.39222 | D4: 539.00999
A6: Response Rate by Campaign | F6: Spend by Category | I6: Response Rate by Age Group | L6: Channel Popularity
A7: Campaign | F7: Category | I7: Age_Group | J7: Average of Response | L7: Channels
A8: Average of AcceptedCmp4 | B8: 0.074686941 | F8: Average of MntFruits | G8: 26.275939 | I8: Young | J8: 0.23255814 | L8: StorePurchases | M8: 5.7956172
A9: Average of AcceptedCmp3 | B9: 0.072898032 | F9: Average of MntSweetProducts | G9: 27.080501 | I9: Middle-aged | J9: 0.15340364 | L9: WebPurchases | M9: 4.0876565
A10: Average of AcceptedCmp5 | B10: 0.072450805 | F10: Average of MntFishProducts | G10: 37.536225 | I10: Senior | J10: 0.1426087 | L10: CatalogPurchases | M10: 2.6632379
A11: Average of AcceptedCmp1 | B11: 0.064400716 | F11: Average of MntGoldProds | G11: 43.983005 | L11: DealsPurchases | M11: 2.3260286
A12: Average of AcceptedCmp2 | B12: 0.013416816 | F12: Average of MntMeatProducts | G12: 166.98345
F13: Average of MntWines | G13: 304.12746

Sheet Dashboard
A1: Marketing Campaign Performance Analysis
A4: Customer Behavior & Response Analysis | 2,236 Customers | Dataset: Kaggle
B11: ='Dashboard Analysis'!A1 -> Overall Response Rate (%) | G11: Avg Spend: Responders vs Non-Responders ($) | L11: ='Dashboard Analysis'!F1 -> Customers in Segment | Q11: ='Dashboard Analysis'!G1 -> Best Performing Campaign (%)
C13: ='Dashboard Analysis'!A2 -> 0.14937388 | H13: ='Dashboard Analysis'!B4 -> 987.39222 | M13: ='Dashboard Analysis'!F2 -> 2236 | R13: ='Dashboard Analysis'!G2 -> 0.074686941
J15: ='Dashboard Analysis'!D4 -> 539.00999
K60: KEY INSIGHTS
B62: =CHAR(198) -> Ж | C62: High-income Seniors drive 77% of responses among top earners - priority audience for future campaigns (view diagram)
B63: =CHAR(198) -> Ж | C63: Responders spend nearly 2x more than non-responders (€987 vs €539)
B64: =CHAR(198) -> Ж | C64: Campaign 2 dramatically underperformed - 1.3% vs 7% average across all campaigns
B65: =CHAR(198) -> Ж | C65: Physical store remains the #1 purchase channel, but Seniors unexpectedly lead in online buying
